Workbook

Sheet 2025年3月电费
A1: 宏发再生资源市场2025年3月电费收费清单
A2: 序号 | B2: 商户姓名 | C2: 分区 | D2: 电表编号 | E2: 本月电表底数 | F2: 上月电表底数 | G2: 倍率 | H2: 用电量 | I2: 单价 | J2: 电费合计 | K2: 补减项 | L2: 备注 | M2: 总计 | N2: 实收
A3: =ROW()-2 -> 1 | B3: 卯声平 | C3: 车间 | D3: 135407 | E3: 803.8 | F3: 713.8 | G3: 60 | H3: =(E3-F3)*G3 -> 5400 | I3: 1.1 | J3: =H3*I3 -> 5940 | M3: =J3+J4+K3+K4 -> 6903.6 | N3: 6904
A4: =ROW()-2 -> 2 | B4: 卯声平 | C4: 宿舍 | D4: 222933 | E4: 6333 | F4: 5457 | G4: 1 | H4: =(E4-F4)*G4 -> 876 | I4: 1.1 | J4: =H4*I4 -> 963.6
A5: =ROW()-2 -> 3 | B5: 王银全 | C5: 车间 | D5: 135406 | E5: 352.9 | F5: 303.8 | G5: 40 | H5: =(E5-F5)*G5 -> 1964 | I5: 1.1 | J5: =H5*I5 -> 2160.4 | M5: =J5+J6+K5+K6 -> 2247.3 | N5: 2247.3
A6: =ROW()-2 -> 4 | C6: 宿舍 | D6: SS101 | E6: 118 | F6: 39 | G6: 1 | H6: =(E6-F6)*G6 -> 79 | I6: 1.1 | J6: =H6*I6 -> 86.9
A7: =ROW()-2 -> 5 | B7: 谢贤祥 | C7: 车间 | D7: 135400 | E7: 10 | F7: 9 | G7: 40 | H7: =(E7-F7)*G7 -> 40 | I7: 1.1 | J7: =H7*I7 -> 44 | M7: =J7+J8+K7+K8 -> 112.2 | N7: 112
A8: =ROW()-2 -> 6 | C8: 宿舍 | D8: SS102 | E8: 323 | F8: 261 | G8: 1 | H8: =(E8-F8)*G8 -> 62 | I8: 1.1 | J8: =H8*I8 -> 68.2
A9: =ROW()-2 -> 7 | B9: 王银福 | C9: 车间 | D9: 135405 | E9: 253.4 | F9: 213.6 | G9: 40 | H9: =(E9-F9)*G9 -> 1592 | I9: 1.1 | J9: =H9*I9 -> 1751.2 | M9: =J9+K9 -> 1751.2 | N9: 1751.2
A10: =ROW()-2 -> 8 | B10: 王文奇 | C10: 车间 | D10: 135401 | E10: 50.4 | F10: 43.8 | G10: 20 | H10: =(E10-F10)*G10 -> 132 | I10: 1.1 | J10: =H10*I10 -> 145.2 | M10: =J10+K10 -> 145.2 | N10: 145.2
A11: =ROW()-2 -> 9 | B11: 李兴平 | C11: 车间一 | D11: 135402 | E11: 379.5 | F11: 320.5 | G11: 20 | H11: =(E11-F11)*G11 -> 1180 | I11: 1.1 | J11: =H11*I11 -> 1298 | M11: =J11+J12+K11+K12 -> 2296.8 | N11: 2296.8
A12: =ROW()-2 -> 10 | C12: 车间二 | D12: 135408 | E12: 144.2 | F12: 121.5 | G12: 40 | H12: =(E12-F12)*G12 -> 908 | I12: 1.1 | J12: =H12*I12 -> 998.8
A13: =ROW()-2 -> 11 | B13: 金耀 | C13: 车间 | D13: 136866 | E13: 172.8 | F13: 157 | G13: 20 | H13: =(E13-F13)*G13 -> 316 | I13: 1.1 | J13: =H13*I13 -> 347.6 | M13: =J13+K13 -> 347.6 | N13: 347.6
A14: =ROW()-2 -> 12 | B14: 代家超 | C14: 车间 | D14: 135847 | E14: 161.2 | F14: 143.9 | G14: 40 | H14: =(E14-F14)*G14 -> 692 | I14: 1.1 | J14: =H14*I14 -> 761.2 | M14: =J14+K14 -> 761.2 | N14: 761
A15: =ROW()-2 -> 13 | B15: 崔宇文 | C15: 车间 | D15: 135848 | E15: 375.2 | F15: 307.7 | G15: 40 | H15: =(E15-F15)*G15 -> 2700 | I15: 1.1 | J15: =H15*I15 -> 2970 | K15: -234 | L15: 购买钢筋欠款 | M15: =J15+K15 -> 2736 | N15: 2736
A16: =ROW()-2 -> 14 | B16: 崔玉文 | C16: 车间 | D16: 135846 | E16: 399.5 | F16: 344.4 | G16: 40 | H16: =(E16-F16)*G16 -> 2204 | I16: 1.1 | J16: =H16*I16 -> 2424.4 | M16: =J16+K16 -> 2424.4 | N16: 2424
A17: =ROW()-2 -> 15 | B17: 祖维成 | C17: 车间 | D17: 135845 | E17: 273.5 | F17: 224.4 | G17: 40 | H17: =(E17-F17)*G17 -> 1964 | I17: 1.1 | J17: =H17*I17 -> 2160.4 | M17: =J17+K17 -> 2160.4 | N17: 2160
A18: =ROW()-2 -> 16 | B18: 崔大冲 | C18: 车间 | D18: 135844 | E18: 21.6 | F18: 16 | G18: 30 | H18: =(E18-F18)*G18 -> 168 | I18: 1.1 | J18: =H18*I18 -> 184.8 | M18: =J18+K18 -> 184.8 | N18: 184
A19: =ROW()-2 -> 17 | B19: 李世坤 | C19: 车间 | D19: 135844 | E19: 26.8 | F19: 21.8 | G19: 30 | H19: =(E19-F19)*G19 -> 150 | I19: 1.1 | J19: =H19*I19 -> 165 | M19: =J19+K19 -> 165 | N19: 165
A20: =ROW()-2 -> 18 | B20: 代家虎 | C20: 车间 | D20: 135850 | E20: 150.1 | F20: 133 | G20: 30 | H20: =(E20-F20)*G20 -> 513 | I20: 1.1 | J20: =H20*I20 -> 564.3 | M20: =J20+K20 -> 564.3 | N20: 564
A21: =ROW()-2 -> 19 | B21: 代家鹏 | C21: 车间 | D21: 135358 | E21: 137.3 | F21: 119.9 | G21: 40 | H21: =(E21-F21)*G21 -> 696 | I21: 1.1 | J21: =H21*I21 -> 765.6 | M21: =J21+K21 -> 765.6 | N21: 765.6
A22: =ROW()-2 -> 20 | B22: 代家俊 | C22: 车间 | D22: 135380 | E22: 196.7 | F22: 167.5 | G22: 40 | H22: =(E22-F22)*G22 -> 1168 | I22: 1.1 | J22: =H22*I22 -> 1284.8 | M22: =J22+K22 -> 1284.8 | N22: 1284
A23: =ROW()-2 -> 21 | B23: 崔汝波 | C23: 车间 | D23: 135376 | E23: 13.1 | F23: 10.4 | G23: 40 | H23: =(E23-F23)*G23 -> 108 | I23: 1.1 | J23: =H23*I23 -> 118.8 | M23: =J23+K23 -> 118.8 | N23: 119
A24: =ROW()-2 -> 22 | B24: 崔大洪 | C24: 车间 | D24: CJ101 | E24: 214 | F24: 141 | G24: 1 | H24: =(E24-F24)*G24 -> 73 | I24: 1.1 | J24: =H24*I24 -> 80.3 | M24: =J24+K24 -> 80.3 | N24: 80.3 | P24: =N24+39.6 -> 119.9
A25: =ROW()-2 -> 23 | B25: 崔大云 | C25: 车间 | D25: CJ102 | E25: 540 | F25: 353 | G25: 1 | H25: =(E25-F25)*G25 -> 187 | I25: 1.1 | J25: =H25*I25 -> 205.7 | M25: =J25+K25 -> 205.7 | N25: 205.7
A26: =ROW()-2 -> 24 | B26: 冯成 | C26: 车间 | D26: 281917 | E26: 17.4 | F26: 0.8 | G26: 100 | H26: =(E26-F26)*G26 -> 1660 | I26: 1.1 | J26: =H26*I26 -> 1826 | M26: =J26+K26 -> 1826 | N26: 1826
A27: =ROW()-2 -> 25 | B27: 崔汝义 | C27: 车间 | D27: 136865 | E27: 164 | F27: 120.5 | G27: 20 | H27: =(E27-F27)*G27 -> 870 | I27: 1.1 | J27: =H27*I27 -> 957 | K27: =-1458.6-159.5 -> -1618.1 | L27: 抵除钢板欠款，欠：661.10 | M27: 0
A28: =ROW()-2 -> 26 | B28: 崔文交 | C28: 车间 | D28: 121780 | E28: 20.1 | F28: 14.2 | G28: 20 | H28: =(E28-F28)*G28 -> 118 | I28: 1.1 | J28: =H28*I28 -> 129.8 | M28: =J28+K28 -> 129.8 | N28: 130
A29: =ROW()-2 -> 27 | B29: 马世平 | C29: 车间 | D29: 135940 | E29: 16.7 | F29: 5.9 | G29: 30 | H29: =(E29-F29)*G29 -> 324 | I29: 1.1 | J29: =H29*I29 -> 356.4 | M29: =J29+K29 -> 356.4 | N29: 357
A30: =ROW()-2 -> 28 | B30: 崔文洪 | C30: 车间 | D30: 121780 | E30: =N35/G30+F30 -> 1625.8233 | F30: 680.7 | G30: 30 | H30: =(E30-F30)*G30 -> 28353.7 | I30: 1.1 | J30: =H30*I30 -> 31189.07 | M30: 0
A31: =ROW()-2 -> 29 | B31: 苏清友 | C31: 施工 | E31: 244 | F31: 0 | G31: 1 | H31: =(E31-F31)*G31 -> 244 | I31: 1.1 | J31: =H31*I31 -> 268.4 | M31: =J31+J32 -> 858 | N31: 858
A32: =ROW()-2 -> 30 | C32: 车间 | E32: 6.7 | F32: 0 | G32: 80 | H32: =(E32-F32)*G32 -> 536 | I32: 1.1 | J32: =H32*I32 -> 589.6
A33: 合计： | J33: =SUM(J3:J32) -> 60805.47 | M33: =SUM(M3:M32) -> 28425.4 | N33: =SUM(N3:N32) -> 28423.7
M34: 购买桶装水 | N34: 70
M35: 结余 | N35: =N33-N34 -> 28353.7

Sheet 2025年4月电费
B1: 宏发再生资源市场2025年4月电费收费清单
A2: 序号 | B2: 商户姓名 | C2: 分区 | D2: 电表编号 | E2: 本月电表底数 | F2: 上月电表底数 | G2: 倍率 | H2: 用电量 | I2: 单价 | J2: 电费合计 | K2: 补减项 | L2: 备注 | M2: 总计 | N2: 实收
A3: =ROW()-2 -> 1 | B3: 卯声平 | C3: 车间 | D3: 135407 | E3: 862 | F3: =VLOOKUP(D3,'2025年3月电费'!D:N,2,0) -> 803.8 | G3: 60 | H3: =(E3-F3)*G3 -> 3492 | I3: 1.1 | J3: =H3*I3 -> 3841.2 | K3: -300 | M3: =J3+J4+K3+K4 -> 4214.4 | N3: 4214.4
A4: =ROW()-2 -> 2 | B4: 卯声平 | C4: 宿舍 | D4: 222933 | E4: 6945 | F4: =VLOOKUP(D4,'2025年3月电费'!D:N,2,0) -> 6333 | G4: 1 | H4: =(E4-F4)*G4 -> 612 | I4: 1.1 | J4: =H4*I4 -> 673.2
A5: =ROW()-2 -> 3 | B5: 王银全 | C5: 车间 | D5: 135406 | E5: 384.8 | F5: =VLOOKUP(D5,'2025年3月电费'!D:N,2,0) -> 352.9 | G5: 40 | H5: =(E5-F5)*G5 -> 1276 | I5: 1.1 | J5: =H5*I5 -> 1403.6 | M5: =J5+J6+K5+K6 -> 1441 | N5: 1441
A6: =ROW()-2 -> 4 | C6: 宿舍 | D6: SS101 | E6: 152 | F6: =VLOOKUP(D6,'2025年3月电费'!D:N,2,0) -> 118 | G6: 1 | H6: =(E6-F6)*G6 -> 34 | I6: 1.1 | J6: =H6*I6 -> 37.4
A7: =ROW()-2 -> 5 | B7: 谢贤祥 | C7: 车间 | D7: 135400 | E7: 10.5 | F7: =VLOOKUP(D7,'2025年3月电费'!D:N,2,0) -> 10 | G7: 40 | H7: =(E7-F7)*G7 -> 20 | I7: 1.1 | J7: =H7*I7 -> 22 | M7: =J7+J8+K7+K8 -> 78.1 | N7: 78.1
A8: =ROW()-2 -> 6 | C8: 宿舍 | D8: SS102 | E8: 374 | F8: =VLOOKUP(D8,'2025年3月电费'!D:N,2,0) -> 323 | G8: 1 | H8: =(E8-F8)*G8 -> 51 | I8: 1.1 | J8: =H8*I8 -> 56.1
A9: =ROW()-2 -> 7 | B9: 王银福 | C9: 车间 | D9: 135405 | E9: 282.2 | F9: =VLOOKUP(D9,'2025年3月电费'!D:N,2,0) -> 253.4 | G9: 40 | H9: =(E9-F9)*G9 -> 1152 | I9: 1.1 | J9: =H9*I9 -> 1267.2 | M9: =J9+K9 -> 1267.2 | N9: 1267
A10: =ROW()-2 -> 8 | B10: 王文奇 | C10: 车间 | D10: 135401 | E10: 56.7 | F10: =VLOOKUP(D10,'2025年3月电费'!D:N,2,0) -> 50.4 | G10: 20 | H10: =(E10-F10)*G10 -> 126 | I10: 1.1 | J10: =H10*I10 -> 138.6 | M10: =J10+K10 -> 138.6 | N10: 139
A11: =ROW()-2 -> 9 | B11: 李兴平 | C11: 车间一 | D11: 135402 | E11: 423.9 | F11: =VLOOKUP(D11,'2025年3月电费'!D:N,2,0) -> 379.5 | G11: 20 | H11: =(E11-F11)*G11 -> 888 | I11: 1.1 | J11: =H11*I11 -> 976.8 | M11: =J11+J12+K11+K12 -> 1746.8 | N11: 1746.8
A12: =ROW()-2 -> 10 | C12: 车间二 | D12: 135408 | E12: 161.7 | F12: =VLOOKUP(D12,'2025年3月电费'!D:N,2,0) -> 144.2 | G12: 40 | H12: =(E12-F12)*G12 -> 700 | I12: 1.1 | J12: =H12*I12 -> 770
A13: =ROW()-2 -> 11 | B13: 金耀 | C13: 车间 | D13: 136866 | E13: 185.3 | F13: =VLOOKUP(D13,'2025年3月电费'!D:N,2,0) -> 172.8 | G13: 20 | H13: =(E13-F13)*G13 -> 250 | I13: 1.1 | J13: =H13*I13 -> 275 | M13: =J13+K13 -> 275 | N13: 275
A14: =ROW()-2 -> 12 | B14: 代家超 | C14: 车间 | D14: 135847 | E14: 169.8 | F14: =VLOOKUP(D14,'2025年3月电费'!D:N,2,0) -> 161.2 | G14: 40 | H14: =(E14-F14)*G14 -> 344 | I14: 1.1 | J14: =H14*I14 -> 378.4 | M14: =J14+K14 -> 378.4 | N14: 378
A15: =ROW()-2 -> 13 | B15: 崔宇文 | C15: 车间 | D15: 135848 | E15: 438 | F15: =VLOOKUP(D15,'2025年3月电费'!D:N,2,0) -> 375.2 | G15: 40 | H15: =(E15-F15)*G15 -> 2512 | I15: 1.1 | J15: =H15*I15 -> 2763.2 | M15: =J15+K15 -> 2763.2 | N15: 2763.2
A16: =ROW()-2 -> 14 | B16: 崔玉文 | C16: 车间 | D16: 135846 | E16: 445.9 | F16: =VLOOKUP(D16,'2025年3月电费'!D:N,2,0) -> 399.5 | G16: 40 | H16: =(E16-F16)*G16 -> 1856 | I16: 1.1 | J16: =H16*I16 -> 2041.6 | M16: =J16+K16 -> 2041.6 | N16: 2041.6
A17: =ROW()-2 -> 15 | B17: 祖维成 | C17: 车间 | D17: 135845 | E17: 308.3 | F17: =VLOOKUP(D17,'2025年3月电费'!D:N,2,0) -> 273.5 | G17: 40 | H17: =(E17-F17)*G17 -> 1392 | I17: 1.1 | J17: =H17*I17 -> 1531.2 | M17: =J17+K17 -> 1531.2 | N17: 1531
A18: =ROW()-2 -> 16 | B18: 崔大冲 | C18: 车间 | D18: 135844 | E18: 28 | F18: =VLOOKUP(D18,'2025年3月电费'!D:N,2,0) -> 21.6 | G18: 30 | H18: =(E18-F18)*G18 -> 192 | I18: 1.1 | J18: =H18*I18 -> 211.2 | M18: =J18+K18 -> 211.2 | N18: 211
A19: =ROW()-2 -> 17 | B19: 李世坤 | C19: 车间 | D19: 135844 | E19: 30.7 | F19: 26.8 | G19: 30 | H19: =(E19-F19)*G19 -> 117 | I19: 1.1 | J19: =H19*I19 -> 128.7 | M19: =J19+K19 -> 128.7 | N19: 128.7
A20: =ROW()-2 -> 18 | B20: 代家虎 | C20: 车间 | D20: 135850 | E20: 161.7 | F20: =VLOOKUP(D20,'2025年3月电费'!D:N,2,0) -> 150.1 | G20: 30 | H20: =(E20-F20)*G20 -> 348 | I20: 1.1 | J20: =H20*I20 -> 382.8 | M20: =J20+K20 -> 382.8 | N20: 382
A21: =ROW()-2 -> 19 | B21: 代家鹏 | C21: 车间 | D21: 135358 | E21: 153 | F21: =VLOOKUP(D21,'2025年3月电费'!D:N,2,0) -> 137.3 | G21: 40 | H21: =(E21-F21)*G21 -> 628 | I21: 1.1 | J21: =H21*I21 -> 690.8 | M21: =J21+K21 -> 690.8 | N21: 690
A22: =ROW()-2 -> 20 | B22: 代家俊 | C22: 车间 | D22: 135380 | E22: 217.7 | F22: =VLOOKUP(D22,'2025年3月电费'!D:N,2,0) -> 196.7 | G22: 40 | H22: =(E22-F22)*G22 -> 840 | I22: 1.1 | J22: =H22*I22 -> 924 | M22: =J22+K22 -> 924 | N22: 924
A23: =ROW()-2 -> 21 | B23: 崔汝波 | C23: 车间 | D23: 135376 | E23: 16.7 | F23: =VLOOKUP(D23,'2025年3月电费'!D:N,2,0) -> 13.1 | G23: 40 | H23: =(E23-F23)*G23 -> 144 | I23: 1.1 | J23: =H23*I23 -> 158.4 | M23: =J23+K23 -> 158.4 | N23: 159
A24: =ROW()-2 -> 22 | B24: 崔大洪 | C24: 车间 | D24: CJ101 | E24: 262 | F24: =VLOOKUP(D24,'2025年3月电费'!D:N,2,0) -> 214 | G24: 1 | H24: =(E24-F24)*G24 -> 48 | I24: 1.1 | J24: =H24*I24 -> 52.8 | M24: =J24+K24 -> 52.8 | N24: 52.8
A25: =ROW()-2 -> 23 | B25: 崔大云 | C25: 车间 | D25: CJ102 | E25: 860 | F25: =VLOOKUP(D25,'2025年3月电费'!D:N,2,0) -> 540 | G25: 1 | H25: =(E25-F25)*G25 -> 320 | I25: 1.1 | J25: =H25*I25 -> 352 | M25: =J25+K25 -> 352 | N25: 352
A26: =ROW()-2 -> 24 | B26: 冯成 | C26: 车间 | D26: 281917 | E26: 25.8 | F26: =VLOOKUP(D26,'2025年3月电费'!D:N,2,0) -> 17.4 | G26: 100 | H26: =(E26-F26)*G26 -> 840 | I26: 1.1 | J26: =H26*I26 -> 924 | M26: =J26+K26 -> 924 | N26: 924
A27: =ROW()-2 -> 25 | B27: 崔汝义 | C27: 车间 | D27: 136865 | E27: 214.5 | F27: =VLOOKUP(D27,'2025年3月电费'!D:N,2,0) -> 164 | G27: 20 | H27: =(E27-F27)*G27 -> 1010 | I27: 1.1 | J27: =H27*I27 -> 1111 | K27: -661.1 | L27: 抵除钢板欠款 | M27: =J27+K27 -> 449.9 | N27: 449.9
A28: =ROW()-2 -> 26 | B28: 崔文交 | C28: 车间 | D28: 121780 | E28: 29 | F28: =VLOOKUP(D28,'2025年3月电费'!D:N,2,0) -> 20.1 | G28: 20 | H28: =(E28-F28)*G28 -> 178 | I28: 1.1 | J28: =H28*I28 -> 195.8 | M28: =J28+K28 -> 195.8 | N28: 195.8
A29: =ROW()-2 -> 27 | B29: 马世平 | C29: 车间 | D29: 135940 | E29: 24.7 | F29: =VLOOKUP(D29,'2025年3月电费'!D:N,2,0) -> 16.7 | G29: 30 | H29: =(E29-F29)*G29 -> 240 | I29: 1.1 | J29: =H29*I29 -> 264 | M29: =J29+K29 -> 264 | N29: 264
A30: =ROW()-2 -> 28 | B30: 崔文洪 | C30: 车间 | D30: 121780 | E30: =1625.82+270.73 -> 1896.55 | F30: 1625.82 | G30: 30 | H30: =(E30-F30)*G30 -> 8121.9 | I30: 1.1 | J30: 0 | M30: =J30+K30 -> 0
A31: =ROW()-2 -> 29 | B31: 苏清友 | C31: 施工 | E31: 256 | F31: 244 | G31: 1 | H31: =(E31-F31)*G31 -> 12 | I31: 1.1 | J31: =H31*I31 -> 13.2 | M31: =J31+J32 -> 12826 | N31: 12826
A32: =ROW()-2 -> 30 | C32: 车间 | E32: 152.3 | F32: 6.7 | G32: 80 | H32: =(E32-F32)*G32 -> 11648 | I32: 1.1 | J32: =H32*I32 -> 12812.8
A33: 合计： | J33: =SUM(J3:J32) -> 34397 | M33: =SUM(M3:M32) -> 33435.9 | N33: =SUM(N3:N32) -> 33434.3
A34: 支付饭钱： | N34: 1900
E35: 挖机烟钱 | N35: =24*4 -> 96
E36: 余波华新烟钱 | N36: =50*2 -> 100
E37: 鞋套+安全绳 | N37: 110
E38: 小蒋烟钱 | N38: 200
E39: 餐费(抢修电缆，晚餐两次) | N39: 470
E40: 崔文洪 | N40: 2000
N41: =N33-SUM(N34:N40) -> 28558.3
E42: 三月工资 | N42: 37600
E43: 差额 | N43: =N42-N41 -> 9041.7

Sheet 2025年5月电费
A1: 宏发再生资源市场2025年5月电费收费清单
A2: 序号 | B2: 商户姓名 | C2: 分区 | D2: 电表编号 | E2: 本月电表底数 | F2: 上月电表底数 | G2: 倍率 | H2: 用电量 | I2: 单价 | J2: 电费合计 | K2: 补减项 | L2: 备注 | M2: 总计 | N2: 实收
A3: =ROW()-2 -> 1 | B3: 卯声平 | C3: 车间 | D3: 135407 | E3: 896 | F3: =VLOOKUP(D3,'2025年4月电费'!D:N,2,0) -> 862 | G3: 60 | H3: =(E3-F3)*G3 -> 2040 | I3: 1.1 | J3: =H3*I3 -> 2244 | M3: =J3+J4+K3+K4 -> 2814.9 | N3: 2815
A4: =ROW()-2 -> 2 | B4: 卯声平 | C4: 宿舍 | D4: 222933 | E4: 7464 | F4: =VLOOKUP(D4,'2025年4月电费'!D:N,2,0) -> 6945 | G4: 1 | H4: =(E4-F4)*G4 -> 519 | I4: 1.1 | J4: =H4*I4 -> 570.9
A5: =ROW()-2 -> 3 | B5: 王银全 | C5: 车间 | D5: 135406 | E5: 412.6 | F5: =VLOOKUP(D5,'2025年4月电费'!D:N,2,0) -> 384.8 | G5: 40 | H5: =(E5-F5)*G5 -> 1112 | I5: 1.1 | J5: =H5*I5 -> 1223.2 | M5: =J5+J6+K5+K6 -> 1237.5 | N5: 1237
C6: 宿舍 | D6: SS101 | E6: 165 | F6: =VLOOKUP(D6,'2025年4月电费'!D:N,2,0) -> 152 | G6: 1 | H6: =(E6-F6)*G6 -> 13 | I6: 1.1 | J6: =H6*I6 -> 14.3
A7: =ROW()-2 -> 5 | B7: 谢贤祥 | C7: 车间 | D7: 135400 | E7: 11.1 | F7: =VLOOKUP(D7,'2025年4月电费'!D:N,2,0) -> 10.5 | G7: 40 | H7: =(E7-F7)*G7 -> 24 | I7: 1.1 | J7: =H7*I7 -> 26.4 | M7: =J7+J8+K7+K8 -> 72.6 | N7: 72
C8: 宿舍 | D8: SS102 | E8: 416 | F8: =VLOOKUP(D8,'2025年4月电费'!D:N,2,0) -> 374 | G8: 1 | H8: =(E8-F8)*G8 -> 42 | I8: 1.1 | J8: =H8*I8 -> 46.2
A9: =ROW()-2 -> 7 | B9: 王银福 | C9: 车间 | D9: 135405 | E9: 306.3 | F9: =VLOOKUP(D9,'2025年4月电费'!D:N,2,0) -> 282.2 | G9: 40 | H9: =(E9-F9)*G9 -> 964 | I9: 1.1 | J9: =H9*I9 -> 1060.4 | M9: =J9+K9 -> 1060.4 | N9: 1060.4
A10: =ROW()-2 -> 8 | B10: 王文奇 | C10: 车间 | D10: 135401 | E10: 59.8 | F10: =VLOOKUP(D10,'2025年4月电费'!D:N,2,0) -> 56.7 | G10: 20 | H10: =(E10-F10)*G10 -> 62 | I10: 1.1 | J10: =H10*I10 -> 68.2 | M10: =J10+K10 -> 68.2 | N10: 68.2
A11: =ROW()-2 -> 9 | B11: 李兴平 | C11: 车间一 | D11: 135402 | E11: 456.6 | F11: =VLOOKUP(D11,'2025年4月电费'!D:N,2,0) -> 423.9 | G11: 20 | H11: =(E11-F11)*G11 -> 654 | I11: 1.1 | J11: =H11*I11 -> 719.4 | K11: -242.5 | L11: 购买铁板 | M11: =J11+J12+K11+K12 -> 1255.7 | N11: 1255.7
C12: 车间二 | D12: 135408 | E12: 179.4 | F12: =VLOOKUP(D12,'2025年4月电费'!D:N,2,0) -> 161.7 | G12: 40 | H12: =(E12-F12)*G12 -> 708 | I12: 1.1 | J12: =H12*I12 -> 778.8
A13: =ROW()-2 -> 11 | B13: 金耀 | C13: 车间 | D13: 136866 | E13: 197.5 | F13: =VLOOKUP(D13,'2025年4月电费'!D:N,2,0) -> 185.3 | G13: 20 | H13: =(E13-F13)*G13 -> 244 | I13: 1.1 | J13: =H13*I13 -> 268.4 | M13: =J13+K13 -> 268.4 | N13: 268.4
A14: =ROW()-2 -> 12 | B14: 代家超 | C14: 车间 | D14: 135847 | E14: 177.3 | F14: =VLOOKUP(D14,'2025年4月电费'!D:N,2,0) -> 169.8 | G14: 40 | H14: =(E14-F14)*G14 -> 300 | I14: 1.1 | J14: =H14*I14 -> 330 | M14: =J14+K14 -> 330 | N14: 330
A15: =ROW()-2 -> 13 | B15: 崔宇文 | C15: 车间 | D15: 135848 | E15: 487.6 | F15: =VLOOKUP(D15,'2025年4月电费'!D:N,2,0) -> 438 | G15: 40 | H15: =(E15-F15)*G15 -> 1984 | I15: 1.1 | J15: =H15*I15 -> 2182.4 | K15: -494 | L15: 购买铁板 | M15: =J15+K15 -> 1688.4 | N15: 1688.4
A16: =ROW()-2 -> 14 | B16: 崔玉文 | C16: 车间 | D16: 135846 | E16: 485 | F16: =VLOOKUP(D16,'2025年4月电费'!D:N,2,0) -> 445.9 | G16: 40 | H16: =(E16-F16)*G16 -> 1564 | I16: 1.1 | J16: =H16*I16 -> 1720.4 | M16: =J16+K16 -> 1720.4 | N16: 1720.4
A17: =ROW()-2 -> 15 | B17: 祖维成 | C17: 车间 | D17: 135845 | E17: 337.5 | F17: =VLOOKUP(D17,'2025年4月电费'!D:N,2,0) -> 308.3 | G17: 40 | H17: =(E17-F17)*G17 -> 1168 | I17: 1.1 | J17: =H17*I17 -> 1284.8 | M17: =J17+K17 -> 1284.8 | N17: 1284
A18: =ROW()-2 -> 16 | B18: 崔大冲 | C18: 车间 | D18: 135844 | E18: 35.2 | F18: =VLOOKUP(D18,'2025年4月电费'!D:N,2,0) -> 28 | G18: 30 | H18: =(E18-F18)*G18 -> 216 | I18: 1.1 | J18: =H18*I18 -> 237.6 | M18: =J18+K18 -> 237.6 | N18: 237.6
A19: =ROW()-2 -> 17 | B19: 李世坤 | C19: 车间 | D19: 135844 | E19: 36.1 | F19: =VLOOKUP(D19,'2025年4月电费'!D:N,2,0) -> 28 | G19: 30 | H19: =(E19-F19)*G19 -> 243 | I19: 1.1 | J19: =H19*I19 -> 267.3 | M19: =J19+K19 -> 267.3 | N19: 267
A20: =ROW()-2 -> 18 | B20: 代家虎 | C20: 车间 | D20: 135850 | E20: 169.7 | F20: =VLOOKUP(D20,'2025年4月电费'!D:N,2,0) -> 161.7 | G20: 30 | H20: =(E20-F20)*G20 -> 240 | I20: 1.1 | J20: =H20*I20 -> 264 | M20: =J20+K20 -> 264 | N20: 264
A21: =ROW()-2 -> 19 | B21: 代家鹏 | C21: 车间 | D21: 135358 | E21: 167.2 | F21: =VLOOKUP(D21,'2025年4月电费'!D:N,2,0) -> 153 | G21: 40 | H21: =(E21-F21)*G21 -> 568 | I21: 1.1 | J21: =H21*I21 -> 624.8 | M21: =J21+K21 -> 624.8 | N21: 624
A22: =ROW()-2 -> 20 | B22: 代家俊 | C22: 车间 | D22: 135380 | E22: 236.4 | F22: =VLOOKUP(D22,'2025年4月电费'!D:N,2,0) -> 217.7 | G22: 40 | H22: =(E22-F22)*G22 -> 748 | I22: 1.1 | J22: =H22*I22 -> 822.8 | M22: =J22+K22 -> 822.8 | N22: 822
A23: =ROW()-2 -> 21 | B23: 崔汝波 | C23: 车间 | D23: 135376 | E23: 20.2 | F23: =VLOOKUP(D23,'2025年4月电费'!D:N,2,0) -> 16.7 | G23: 40 | H23: =(E23-F23)*G23 -> 140 | I23: 1.1 | J23: =H23*I23 -> 154 | M23: =J23+K23 -> 154 | N23: 154
A24: =ROW()-2 -> 22 | B24: 崔大洪 | C24: 车间 | D24: CJ101 | E24: 315 | F24: =VLOOKUP(D24,'2025年4月电费'!D:N,2,0) -> 262 | G24: 1 | H24: =(E24-F24)*G24 -> 53 | I24: 1.1 | J24: =H24*I24 -> 58.3 | M24: =J24+K24 -> 58.3 | N24: 58.3
A25: =ROW()-2 -> 23 | B25: 崔大云 | C25: 车间 | D25: CJ102 | E25: 1123 | F25: =VLOOKUP(D25,'2025年4月电费'!D:N,2,0) -> 860 | G25: 1 | H25: =(E25-F25)*G25 -> 263 | I25: 1.1 | J25: =H25*I25 -> 289.3 | M25: =J25+K25 -> 289.3 | N25: 289.3
A26: =ROW()-2 -> 24 | B26: 冯成 | C26: 车间 | D26: 281917 | E26: 30.6 | F26: =VLOOKUP(D26,'2025年4月电费'!D:N,2,0) -> 25.8 | G26: 100 | H26: =(E26-F26)*G26 -> 480 | I26: 1.1 | J26: =H26*I26 -> 528 | M26: =J26+K26 -> 528 | N26: 528
A27: =ROW()-2 -> 25 | B27: 崔汝义 | C27: 车间 | D27: 136865 | E27: 243.6 | F27: =VLOOKUP(D27,'2025年4月电费'!D:N,2,0) -> 214.5 | G27: 20 | H27: =(E27-F27)*G27 -> 582 | I27: 1.1 | J27: =H27*I27 -> 640.2 | M27: =J27+K27 -> 640.2 | N27: 640.2
A28: =ROW()-2 -> 26 | B28: 崔文交 | C28: 车间 | D28: 121780 | E28: 35.8 | F28: =VLOOKUP(D28,'2025年4月电费'!D:N,2,0) -> 29 | G28: 20 | H28: =(E28-F28)*G28 -> 136 | I28: 1.1 | J28: =H28*I28 -> 149.6 | M28: =J28+K28 -> 149.6 | N28: 150
A29: =ROW()-2 -> 27 | B29: 马世平 | C29: 车间 | D29: 135940 | E29: 29.7 | F29: =VLOOKUP(D29,'2025年4月电费'!D:N,2,0) -> 24.7 | G29: 30 | H29: =(E29-F29)*G29 -> 150 | I29: 1.1 | J29: =H29*I29 -> 165 | M29: =J29+K29 -> 165 | N29: 165
A30: =ROW()-2 -> 28 | B30: 崔文洪 | C30: 车间 | D30: 121780 | E30: 2097.6 | F30: =1625.82+270.73 -> 1896.55 | G30: 30 | H30: =(E30-F30)*G30 -> 6031.5 | I30: 1.1 | J30: =H30*I30 -> 6634.65 | M30: 0
A31: =ROW()-2 -> 29 | B31: 苏清友 | C31: 车间 | D31: 134768 | E31: 284.8 | F31: 152.3 | G31: 80 | H31: =(E31-F31)*G31 -> 10600 | I31: 1.1 | J31: =H31*I31 -> 11660 | M31: =J31+K31 -> 11660 | N31: 11660
A32: 合计： | J32: =SUM(J3:J31) -> 35033.35 | M32: =SUM(M3:M31) -> 27662.2 | N32: =SUM(N3:N31) -> 27658.9
A34: 支付饭钱： | N34: 2160
A35: 桶装水： | N35: 140
A36: 草酸：10*10kg | N36: 219
A37: 大号垃圾袋：60只*21包 | N37: =21*7.99 -> 167.79
A38: 电缆：3*185+2*95铝芯线46米 | N38: 2740
A39: 宽带费： | N39: 1000
A40: 电费： | N40: 35622.89
A41: 变压器至苏总电缆沟清理： | N41: 1700
A42: 支出小计： | N42: =SUM(N34:N41) -> 43749.68
A43: 差额： | N43: =N42-N32 -> 16090.78

Sheet 抄表数据临时表
A1: 商户姓名 | B1: 本月抄表电量 | C1: 上月抄表电量 | D1: 倍率 | E1: 实际用电量 | F1: 单价 | G1: 电费金额 | H1: 表号
A2: 食堂厨房 | B2: 6110 | C2: 6110 | D2: 1 | E2: =(B2-C2)*D2 -> 0 | F2: 1.1 | G2: =ROUNDUP((E2*F2),0) -> 0 | H2: 763170
A3: 食堂餐厅 | B3: 4022 | C3: 4022 | D3: 1 | E3: =(B3-C3)*D3 -> 0 | F3: 1.1 | G3: =ROUNDUP((E3*F3),0) -> 0 | H3: 272501
A4: 卯声平 | B4: 803.8 | C4: 713.8 | D4: 60 | E4: =(B4-C4)*D4 -> 5400 | F4: 1.1 | G4: =ROUNDUP((E4*F4),0) -> 5940 | H4: 135407
A5: 卯声平宿舍 | B5: 6333 | C5: 5457 | D5: 1 | E5: =(B5-C5)*D5 -> 876 | F5: 1.1 | G5: =ROUNDUP((E5*F5),0) -> 964 | H5: 222933
A6: 王银全车间 | B6: 352.9 | C6: 303.8 | D6: 40 | E6: =(B6-C6)*D6 -> 1964 | F6: 1.1 | G6: =ROUNDUP((E6*F6),0) -> 2161 | H6: 135406
A7: 王银全宿舍 | B7: 118 | C7: 39 | D7: 1 | E7: =(B7-C7)*D7 -> 79 | F7: 1.1 | G7: =ROUNDUP((E7*F7),0) -> 87 | H7: 无
B8: 2025年3月3日入住，3月17日入住，共两间300元每月。
A9: 谢贤祥 | B9: 10 | C9: 9 | D9: 40 | E9: =(B9-C9)*D9 -> 40 | F9: 1.1 | G9: =ROUNDUP((E9*F9),0) -> 44 | H9: 135400
A10: 谢贤祥宿舍 | B10: 323 | C10: 261 | D10: 1 | E10: =(B10-C10)*D10 -> 62 | F10: 1.1 | G10: =ROUNDUP((E10*F10),0) -> 69 | H10: 无
A11: 王银福 | B11: 253.4 | C11: 213.6 | D11: 40 | E11: =(B11-C11)*D11 -> 1592 | F11: 1.1 | G11: =ROUNDUP((E11*F11),0) -> 1752 | H11: 135405
A12: 王文奇 | B12: 50.4 | C12: 43.8 | D12: 20 | E12: =(B12-C12)*D12 -> 132 | F12: 1.1 | G12: =ROUNDUP((E12*F12),0) -> 146 | H12: 135401
A13: 李兴平1 | B13: 379.5 | C13: 320.5 | D13: 20 | E13: =(B13-C13)*D13 -> 1180 | F13: 1.1 | G13: =ROUNDUP((E13*F13),0) -> 1298 | H13: 135402
A14: 李兴平2 | B14: 144.2 | C14: 121.5 | D14: 40 | E14: =(B14-C14)*D14 -> 908 | F14: 1.1 | G14: =ROUNDUP((E14*F14),0) -> 999 | H14: 135408
A15: 金 耀 | B15: 172.8 | C15: 157 | D15: 20 | E15: =(B15-C15)*D15 -> 316 | F15: 1.1 | G15: =ROUNDUP((E15*F15),0) -> 348 | H15: 136866
A16: 办公楼 | B16: 1510 | C16: 1049 | D16: 1 | E16: =(B16-C16)*D16 -> 461 | H16: 无
A17: 张祥恩 | B17: 2113 | C17: 1630 | D17: 1 | E17: =(B17-C17)*D17 -> 483 | H17: 无
A18: 磅房门卫 | B18: 3810 | C18: 2900 | D18: 1 | E18: =(B18-C18)*D18 -> 910 | H18: 无
A19: 深井泵 | B19: 2532 | C19: 1895 | D19: 1 | E19: =(B19-C19)*D19 -> 637 | H19: 无
A20: 增压泵 | B20: 1415 | C20: 1031 | D20: 1 | E20: =(B20-C20)*D20 -> 384 | H20: 无
A21: 商家总 | E21: =SUM(E2:E15) -> 12549
A22: 总 表 | B22: 338.3 | C22: 297.7 | D22: 400 | E22: =(B22-C22)*D22 -> 16240 | H22: 135404
A23: 代家超 | B23: 161.2 | C23: 143.9 | D23: 40 | E23: =(B23-C23)*D23 -> 692 | F23: 1.1 | G23: =ROUNDUP((E23*F23),0) -> 762 | H23: 135847
A24: 崔宇文 | B24: 375.2 | C24: 307.7 | D24: 40 | E24: =(B24-C24)*D24 -> 2700 | F24: 1.1 | G24: =ROUNDUP((E24*F24),0) -> 2970 | H24: 135848
B25: 钢筋做排污管支架，90公斤，2.6元每公斤，共234元
A26: 崔玉文 | B26: 399.5 | C26: 344.4 | D26: 40 | E26: =(B26-C26)*D26 -> 2204 | F26: 1.1 | G26: =ROUNDUP((E26*F26),0) -> 2425 | H26: 135846
A27: 祖维成 | B27: 273.5 | C27: 224.4 | D27: 40 | E27: =(B27-C27)*D27 -> 1964 | F27: 1.1 | G27: =ROUNDUP((E27*F27),0) -> 2161 | H27: 135845
A28: 崔大冲 | B28: 21.6 | C28: 16 | D28: 30 | E28: =(B28-C28)*D28 -> 168 | F28: 1.1 | G28: =ROUNDUP((E28*F28),0) -> 185 | H28: 135844
A29: 李世坤 | B29: 26.8 | C29: 21.8 | D29: 30 | E29: =(B29-C29)*D29 -> 150 | F29: 1.1 | G29: =ROUNDUP((E29*F29),0) -> 165 | H29: 135851
A30: 代家虎 | B30: 150.1 | C30: 133 | D30: 30 | E30: =(B30-C30)*D30 -> 513 | F30: 1.1 | G30: =ROUNDUP((E30*F30),0) -> 565 | H30: 135850
A31: 代家鹏 | B31: 137.3 | C31: 119.9 | D31: 40 | E31: =(B31-C31)*D31 -> 696 | F31: 1.1 | G31: =ROUNDUP((E31*F31),0) -> 766 | H31: 135358
A32: 代家俊 | B32: 196.7 | C32: 167.5 | D32: 40 | E32: =(B32-C32)*D32 -> 1168 | F32: 1.1 | G32: =ROUNDUP((E32*F32),0) -> 1285 | H32: 135380
A33: 崔汝波 | B33: 13.1 | C33: 10.4 | D33: 40 | E33: =(B33-C33)*D33 -> 108 | F33: 1.1 | G33: =ROUNDUP((E33*F33),0) -> 119 | H33: 135376
A34: 崔大洪 | B34: 214 | C34: 141 | D34: 1 | E34: =(B34-C34)*D34 -> 73 | F34: 1.1 | G34: =ROUNDUP((E34*F34),0) -> 81 | H34: 无
A35: 崔大云 | B35: 540 | C35: 353 | D35: 1 | E35: =(B35-C35)*D35 -> 187 | F35: 1.1 | G35: =ROUNDUP((E35*F35),0) -> 206 | H35: 无
A36: 冯 成 | B36: 17.4 | C36: 0.8 | D36: 100 | E36: =(B36-C36)*D36 -> 1660 | F36: 1.1 | G36: =ROUNDUP((E36*F36),0) -> 1826 | H36: 281917
A37: 消防泵 | B37: 120 | C37: 79 | D37: 1 | E37: =(B37-C37)*D37 -> 41 | H37: 无
A38: 商家总 | E38: =SUM(E23:E36) -> 12283
A39: 总 表 | B39: 178 | C39: 147.4 | D39: 400 | E39: =(B39-C39)*D39 -> 12240 | H39: 135849
A40: 崔汝义 | B40: 164 | C40: 120.5 | D40: 20 | E40: =(B40-C40)*D40 -> 870 | F40: 1.1 | G40: =ROUNDUP((E40*F40),0) -> 957 | H40: 136865
B41: 槽钢做配电柜支架共72.5公斤，2.2元每公斤共159.5元
A42: 崔文交 | B42: 20.1 | C42: 14.2 | D42: 20 | E42: =(B42-C42)*D42 -> 118 | F42: 1.1 | G42: =ROUNDUP((E42*F42),0) -> 130 | H42: 121780
A43: 马世平 | B43: 16.7 | C43: 5.9 | D43: 30 | E43: =(B43-C43)*D43 -> 324 | F43: 1.1 | G43: =ROUNDUP((E43*F43),0) -> 357 | H43: 135940
A44: 商家总 | E44: =E40+E42+E43 -> 1312
A45: 总 表 | B45: 11 | C45: 7.8 | D45: 400 | E45: =(B45-C45)*D45 -> 1280 | H45: 121775
A46: 崔文洪 | H46: 135679
A47: 苏清友施工 | B47: 244 | C47: 0 | D47: 1 | E47: =(B47-C47)*D47 -> 244 | F47: 1.1 | G47: =ROUNDUP((E47*F47),0) -> 269
A48: 苏清友车间 | B48: 6.7 | C48: 0 | D48: 80 | E48: =(B48-C48)*D48 -> 536 | F48: 1.1 | G48: =ROUNDUP((E48*F48),0) -> 590 | H48: 134768

Sheet 2025年6月水电费
A1: 宏发再生资源市场2025年6月水电费收费清单
A2: 序号 | B2: 商户姓名 | C2: 分区 | D2: 电表编号 | E2: 本月电表底数 | F2: 上月电表底数 | G2: 倍率 | H2: 用电量 | I2: 电费单价 | J2: 电费合计 | K2: 上月水表底数 | L2: 本月水表底数 | M2: 水费单价 | N2: 水费合计 | O2: 补减项 | P2: 备注 | Q2: 总计 | R2: 实收
A3: =ROW()-2 -> 1 | B3: 卯声平 | C3: 车间 | D3: 135407 | E3: 1008.7 | F3: 896 | G3: 60 | H3: =(E3-F3)*G3 -> 6762 | I3: 1.1 | J3: =H3*I3 -> 7438.2 | K3: 76 | L3: 146 | M3: 4.4 | N3: =(L3-K3)*M3 -> 308 | Q3: =J3+J4+O3+O4+N3+N4 -> 8636.1 | R3: 8636
C4: 宿舍 | D4: 222933 | E4: 8021 | F4: 7464 | G4: 1 | H4: =(E4-F4)*G4 -> 557 | I4: 1.1 | J4: =H4*I4 -> 612.7 | K4: 119 | L4: 182 | M4: 4.4 | N4: =(L4-K4)*M4 -> 277.2
A5: 2 | B5: 王银全 | C5: 车间 | D5: 135406 | E5: 442.1 | F5: 412.6 | G5: 40 | H5: =(E5-F5)*G5 -> 1180 | I5: 1.1 | J5: =H5*I5 -> 1298 | K5: 94 | L5: 164 | M5: 4.4 | N5: =(L5-K5)*M5 -> 308 | Q5: =J5+J6+O5+O6+N5+N6 -> 1626.9 | R5: 1626
C6: 宿舍 | D6: SS101 | E6: 184 | F6: 165 | G6: 1 | H6: =(E6-F6)*G6 -> 19 | I6: 1.1 | J6: =H6*I6 -> 20.9 | K6: 0 | L6: 0 | M6: 4.4 | N6: =(L6-K6)*M6 -> 0
A7: 3 | B7: 谢贤祥 | C7: 车间 | D7: 135400 | E7: 11.7 | F7: 11.1 | G7: 40 | H7: =(E7-F7)*G7 -> 24 | I7: 1.1 | J7: =H7*I7 -> 26.4 | K7: 44 | L7: 55 | M7: 4.4 | N7: =(L7-K7)*M7 -> 48.4 | Q7: =J7+J8+O7+O8+N7+N8 -> 157.3 | R7: 157.3
C8: 宿舍 | D8: SS102 | E8: 459 | F8: 416 | G8: 1 | H8: =(E8-F8)*G8 -> 43 | I8: 1.1 | J8: =H8*I8 -> 47.3 | K8: 5 | L8: 13 | M8: 4.4 | N8: =(L8-K8)*M8 -> 35.2
A9: 4 | B9: 王银福 | C9: 车间 | D9: 135405 | E9: 335.7 | F9: 306.3 | G9: 40 | H9: =(E9-F9)*G9 -> 1176 | I9: 1.1 | J9: =H9*I9 -> 1293.6 | K9: 92 | L9: 155 | M9: 4.4 | N9: =(L9-K9)*M9 -> 277.2 | Q9: =J9+O9+N9 -> 1570.8 | R9: 1293.6 | S9: =Q9-R9 -> 277.2
A10: 5 | B10: 王文奇 | C10: 车间 | D10: 135401 | E10: 64 | F10: 59.8 | G10: 20 | H10: =(E10-F10)*G10 -> 84 | I10: 1.1 | J10: =H10*I10 -> 92.4 | K10: 7 | L10: 8 | M10: 4.4 | N10: =(L10-K10)*M10 -> 4.4 | Q10: =J10+O10+N10 -> 96.8 | R10: 92.4
A11: 6 | B11: 李兴平 | C11: 车间一 | D11: 135402 | E11: 502.8 | F11: 456.6 | G11: 20 | H11: =(E11-F11)*G11 -> 924 | I11: 1.1 | J11: =H11*I11 -> 1016.4 | K11: 101 | L11: 166 | M11: 4.4 | N11: =(L11-K11)*M11 -> 286 | Q11: =J11+J12+O11+O12+N11+N12 -> 2283.6 | R11: 2283.6
C12: 车间二 | D12: 135408 | E12: 201.7 | F12: 179.4 | G12: 40 | H12: =(E12-F12)*G12 -> 892 | I12: 1.1 | J12: =H12*I12 -> 981.2 | K12: 0 | L12: 0 | M12: 4.4 | N12: =(L12-K12)*M12 -> 0
A13: 7 | B13: 金耀 | C13: 车间 | D13: 136866 | E13: 210.1 | F13: 197.5 | G13: 20 | H13: =(E13-F13)*G13 -> 252 | I13: 1.1 | J13: =H13*I13 -> 277.2 | K13: 13 | L13: 20 | M13: 4.4 | N13: =(L13-K13)*M13 -> 30.8 | Q13: =J13+O13+N13 -> 308 | R13: 308
A14: 8 | B14: 代家超 | C14: 车间 | D14: 135847 | E14: 187.6 | F14: 177.3 | G14: 40 | H14: =(E14-F14)*G14 -> 412 | I14: 1.1 | J14: =H14*I14 -> 453.2 | K14: 43 | L14: 61 | M14: 4.4 | N14: =(L14-K14)*M14 -> 79.2 | Q14: =J14+O14+N14 -> 532.4 | R14: 532 | S14: 45848
A15: 9 | B15: 崔宇文 | C15: 车间 | D15: 135848 | E15: 545.8 | F15: 487.6 | G15: 40 | H15: =(E15-F15)*G15 -> 2328 | I15: 1.1 | J15: =H15*I15 -> 2560.8 | K15: 10 | L15: 18 | M15: 4.4 | N15: =(L15-K15)*M15 -> 35.2 | Q15: =J15+O15+N15 -> 2596 | R15: 2596
A16: 10 | B16: 崔玉文 | C16: 车间 | D16: 135846 | E16: 532.6 | F16: 485 | G16: 40 | H16: =(E16-F16)*G16 -> 1904 | I16: 1.1 | J16: =H16*I16 -> 2094.4 | K16: 3 | L16: 5 | M16: 4.4 | N16: =(L16-K16)*M16 -> 8.8 | Q16: =J16+O16+N16 -> 2103.2 | R16: 2103
A17: 11 | B17: 祖维成 | C17: 车间 | D17: 135845 | E17: 366.5 | F17: 337.5 | G17: 40 | H17: =(E17-F17)*G17 -> 1160 | I17: 1.1 | J17: =H17*I17 -> 1276 | K17: 80 | L17: 155 | M17: 4.4 | N17: =(L17-K17)*M17 -> 330 | Q17: =J17+O17+N17 -> 1606 | R17: 1606
A18: 12 | B18: 崔大冲 | C18: 车间 | D18: 135844 | E18: 41.9 | F18: 35.2 | G18: 30 | H18: =(E18-F18)*G18 -> 201 | I18: 1.1 | J18: =H18*I18 -> 221.1 | K18: 3 | L18: 17 | M18: 4.4 | N18: =(L18-K18)*M18 -> 61.6 | Q18: =J18+O18+N18 -> 282.7 | R18: 280.27
A19: 13 | B19: 李世坤 | C19: 车间 | D19: 135844 | E19: 41.2 | F19: 36.1 | G19: 30 | H19: =(E19-F19)*G19 -> 153 | I19: 1.1 | J19: =H19*I19 -> 168.3 | K19: 3 | L19: 19 | M19: 4.4 | N19: =(L19-K19)*M19 -> 70.4 | Q19: =J19+O19+N19 -> 238.7 | R19: 238.7 | S19: 45848
A20: 14 | B20: 代家虎 | C20: 车间 | D20: 135850 | E20: 179.1 | F20: 169.7 | G20: 30 | H20: =(E20-F20)*G20 -> 282 | I20: 1.1 | J20: =H20*I20 -> 310.2 | K20: 24 | L20: 37 | M20: 4.4 | N20: =(L20-K20)*M20 -> 57.2 | Q20: =J20+O20+N20 -> 367.4 | R20: 367 | S20: 45848
A21: 15 | B21: 代家鹏 | C21: 车间 | D21: 135358 | E21: 183.5 | F21: 167.2 | G21: 40 | H21: =(E21-F21)*G21 -> 652 | I21: 1.1 | J21: =H21*I21 -> 717.2 | K21: 53 | L21: 105 | M21: 4.4 | N21: =(L21-K21)*M21 -> 228.8 | Q21: =J21+O21+N21 -> 946 | R21: 946
A22: 16 | B22: 代家俊 | C22: 车间 | D22: 135380 | E22: 256.6 | F22: 236.4 | G22: 40 | H22: =(E22-F22)*G22 -> 808 | I22: 1.1 | J22: =H22*I22 -> 888.8 | K22: 49 | L22: 110 | M22: 4.4 | N22: =(L22-K22)*M22 -> 268.4 | Q22: =J22+O22+N22 -> 1157.2 | R22: 1157
A23: 17 | B23: 崔汝波 | C23: 车间 | D23: 135376 | E23: 24.2 | F23: 20.2 | G23: 40 | H23: =(E23-F23)*G23 -> 160 | I23: 1.1 | J23: =H23*I23 -> 176 | K23: 42 | L23: 59 | M23: 4.4 | N23: =(L23-K23)*M23 -> 74.8 | Q23: =J23+O23+N23 -> 250.8 | R23: =75+176 -> 251 | S23: 45848
A24: 18 | B24: 崔大洪 | C24: 车间 | D24: CJ101 | E24: 367 | F24: 315 | G24: 1 | H24: =(E24-F24)*G24 -> 52 | I24: 1.1 | J24: =H24*I24 -> 57.2 | K24: 5 | L24: 9 | M24: 4.4 | N24: =(L24-K24)*M24 -> 17.6 | Q24: =J24+O24+N24 -> 74.8 | R24: 75
A25: 19 | B25: 崔大云 | C25: 车间 | D25: CJ102 | E25: 1491 | F25: 1123 | G25: 1 | H25: =(E25-F25)*G25 -> 368 | I25: 1.1 | J25: =H25*I25 -> 404.8 | K25: 12 | L25: 38 | M25: 4.4 | N25: =(L25-K25)*M25 -> 114.4 | Q25: =J25+O25+N25 -> 519.2 | R25: 519.2
A26: 20 | B26: 冯成 | C26: 车间 | D26: 281917 | E26: 42.1 | F26: 30.6 | G26: 100 | H26: =(E26-F26)*G26 -> 1150 | I26: 1.1 | J26: =H26*I26 -> 1265 | K26: 0 | L26: 9 | M26: 4.4 | N26: =(L26-K26)*M26 -> 39.6 | Q26: =J26+O26+N26 -> 1304.6 | R26: 1304.6
A27: 21 | B27: 崔汝义 | C27: 车间 | D27: 136865 | E27: 267.5 | F27: 243.6 | G27: 20 | H27: =(E27-F27)*G27 -> 478 | I27: 1.1 | J27: =H27*I27 -> 525.8 | K27: 2 | L27: 4 | M27: 4.4 | N27: =(L27-K27)*M27 -> 8.8 | Q27: =J27+O27+N27 -> 534.6 | R27: 534.6
A28: 22 | B28: 崔文交 | C28: 车间 | D28: 121780 | E28: 45.6 | F28: 35.8 | G28: 20 | H28: =(E28-F28)*G28 -> 196 | I28: 1.1 | J28: =H28*I28 -> 215.6 | K28: 7 | L28: 38 | M28: 4.4 | N28: =(L28-K28)*M28 -> 136.4 | Q28: =J28+O28+N28 -> 352 | R28: 352 | S28: 45848
A29: 23 | B29: 马世平 | C29: 车间 | D29: 135940 | E29: 33.9 | F29: 29.7 | G29: 30 | H29: =(E29-F29)*G29 -> 126 | I29: 1.1 | J29: =H29*I29 -> 138.6 | K29: 0 | L29: 3 | M29: 4.4 | N29: =(L29-K29)*M29 -> 13.2 | Q29: =J29+O29+N29 -> 151.8 | R29: 152
A30: 24 | B30: 崔文洪 | C30: 生活 | K30: 126 | L30: 258 | M30: 4.4 | N30: =(L30-K30)*M30 -> 580.8 | Q30: =J30+O30+J31+N30+N31+O31 -> 849.2 | R30: 850
C31: 车间 | D31: 121780 | E31: 2284.3 | F31: 2097.6 | G31: 0 | H31: =(E31-F31)*G31 -> 0 | I31: 1.1 | J31: =H31*I31 -> 0 | K31: 12 | L31: 73 | M31: 4.4 | N31: =(L31-K31)*M31 -> 268.4
A32: 25 | B32: 苏清友 | C32: 车间 | D32: 134768 | E32: 389.7 | F32: 284.8 | G32: 80 | H32: =(E32-F32)*G32 -> 8392 | I32: 1.1 | J32: =H32*I32 -> 9231.2 | K32: 0 | L32: 23 | M32: 4.4 | N32: =(L32-K32)*M32 -> 101.2 | Q32: =J32+O32+N32 -> 9332.4 | R32: 9332.4
A33: 26 | B33: 杨文仁 | C33: 车间 | D33: 135939 | E33: 5.2 | F33: 0 | G33: 80 | H33: =(E33-F33)*G33 -> 416 | I33: 1.1 | J33: =H33*I33 -> 457.6 | K33: 0 | L33: 0 | M33: 4.4 | N33: =(L33-K33)*M33 -> 0 | Q33: =J33+O33+N33 -> 457.6
A34: 合计： | J34: =SUM(J3:J33) -> 34266.1 | N34: =SUM(N3:N32) -> 4070 | Q34: =SUM(Q3:Q33) -> 38336.1 | R34: =SUM(R3:R33) -> 37593.67
A35: 餐费： | R35: 1965
A36: 桶装水： | J36: 29638.49 | R36: 105
A37: 方便米饭： | C37: 2箱*36盒 | R37: 346.4
A38: 电费： | R38: 25763.78
J40: =J34-J36 -> 4627.61 | R40: =R34-SUM(R35:R39) -> 9413.49

Sheet 2025年7月水电费
A1: 宏发再生资源市场2025年7月电费收费清单
A2: 序号 | B2: 商户姓名 | C2: 分区 | D2: 电表编号 | E2: 本月电表底数 | F2: 上月电表底数 | G2: 倍率 | H2: 用电量 | I2: 电费单价 | J2: 电费合计 | K2: 补减项 | L2: 备注 | M2: 总计 | N2: 实收
A3: =ROW()-2 -> 1 | B3: 卯声平 | C3: 车间 | D3: 135407 | E3: 1077.3 | F3: 1008.7 | G3: 60 | H3: =(E3-F3)*G3 -> 4116 | I3: 1.1 | J3: =H3*I3 -> 4527.6 | M3: =J3+J4+K3+K4 -> 5210.7 | N3: 5210
C4: 宿舍 | D4: 222933 | E4: 8642 | F4: 8021 | G4: 1 | H4: =(E4-F4)*G4 -> 621 | I4: 1.1 | J4: =H4*I4 -> 683.1
A5: 2 | B5: 王银全 | C5: 车间 | D5: 135406 | E5: 467.2 | F5: 442.1 | G5: 40 | H5: =(E5-F5)*G5 -> 1004 | I5: 1.1 | J5: =H5*I5 -> 1104.4 | M5: =J5+J6+K5+K6 -> 1104.4 | N5: 1104
C6: 宿舍 | D6: SS101 | E6: 184 | F6: 184 | G6: 1 | H6: =(E6-F6)*G6 -> 0 | I6: 1.1 | J6: =H6*I6 -> 0
A7: 3 | B7: 谢贤祥 | C7: 车间 | D7: 135400 | E7: 12.5 | F7: 11.7 | G7: 40 | H7: =(E7-F7)*G7 -> 32 | I7: 1.1 | J7: =H7*I7 -> 35.2 | M7: =J7+J8+K7+K8 -> 138.6 | N7: 138.6
C8: 宿舍 | D8: SS102 | E8: 553 | F8: 459 | G8: 1 | H8: =(E8-F8)*G8 -> 94 | I8: 1.1 | J8: =H8*I8 -> 103.4
A9: 4 | B9: 王银福 | C9: 车间 | D9: 135405 | E9: 362.1 | F9: 335.7 | G9: 40 | H9: =(E9-F9)*G9 -> 1056 | I9: 1.1 | J9: =H9*I9 -> 1161.6 | M9: =J9+K9 -> 1161.6 | N9: 1161
A10: 5 | B10: 王文奇 | C10: 车间 | D10: 135401 | E10: 68.6 | F10: 64 | G10: 20 | H10: =(E10-F10)*G10 -> 92 | I10: 1.1 | J10: =H10*I10 -> 101.2 | M10: =J10+K10 -> 101.2 | N10: 101
A11: 6 | B11: 李兴平 | C11: 车间一 | D11: 135402 | E11: 551.6 | F11: 502.8 | G11: 20 | H11: =(E11-F11)*G11 -> 976 | I11: 1.1 | J11: =H11*I11 -> 1073.6 | M11: =J11+J12+K11+K12 -> 2046 | N11: 2046
C12: 车间二 | D12: 135408 | E12: 223.8 | F12: 201.7 | G12: 40 | H12: =(E12-F12)*G12 -> 884 | I12: 1.1 | J12: =H12*I12 -> 972.4
A13: 7 | B13: 金耀 | C13: 车间 | D13: 136866 | E13: 222.1 | F13: 210.1 | G13: 20 | H13: =(E13-F13)*G13 -> 240 | I13: 1.1 | J13: =H13*I13 -> 264 | M13: =J13+K13 -> 264 | N13: 264
A14: 8 | B14: 代家超 | C14: 车间 | D14: 135847 | E14: 197.7 | F14: 187.6 | G14: 40 | H14: =(E14-F14)*G14 -> 404 | I14: 1.1 | J14: =H14*I14 -> 444.4 | M14: =J14+K14 -> 444.4 | N14: 444
A15: 9 | B15: 崔宇文 | C15: 车间 | D15: 135848 | E15: 606.2 | F15: 545.8 | G15: 40 | H15: =(E15-F15)*G15 -> 2416 | I15: 1.1 | J15: =H15*I15 -> 2657.6 | M15: =J15+K15 -> 2657.6 | N15: 2657.6
A16: 10 | B16: 崔玉文 | C16: 车间 | D16: 135846 | E16: 579.9 | F16: 532.6 | G16: 40 | H16: =(E16-F16)*G16 -> 1892 | I16: 1.1 | J16: =H16*I16 -> 2081.2 | M16: =J16+K16+J17+K17 -> 2644.4 | N16: 2644
D17: 135379 | E17: 6.4 | F17: 0 | G17: 80 | H17: =(E17-F17)*G17 -> 512 | I17: 1.1 | J17: =H17*I17 -> 563.2
A18: 11 | B18: 祖维成 | C18: 车间 | D18: 135845 | E18: 394.2 | F18: 366.5 | G18: 40 | H18: =(E18-F18)*G18 -> 1108 | I18: 1.1 | J18: =H18*I18 -> 1218.8 | M18: =J18+K18 -> 1218.8 | N18: 1218.8 | O18: =N18-M18 -> 0 | P18: 1276 | Q18: =P18-N18 -> 57.2
A19: 12 | B19: 崔大冲 | C19: 车间 | D19: 135844 | E19: 48.4 | F19: 41.9 | G19: 30 | H19: =(E19-F19)*G19 -> 195 | I19: 1.1 | J19: =H19*I19 -> 214.5 | M19: =J19+K19 -> 214.5 | N19: 214.5
A20: 13 | B20: 李世坤 | C20: 车间 | D20: 135844 | E20: 54.5 | F20: 41.2 | G20: 30 | H20: =(E20-F20)*G20 -> 399 | I20: 1.1 | J20: =H20*I20 -> 438.9 | M20: =J20+K20 -> 438.9 | N20: 438
A21: 14 | B21: 代家虎 | C21: 车间 | D21: 135850 | E21: 187 | F21: 179.1 | G21: 30 | H21: =(E21-F21)*G21 -> 237 | I21: 1.1 | J21: =H21*I21 -> 260.7 | M21: =J21+K21 -> 260.7 | N21: 260
A22: 15 | B22: 代家鹏 | C22: 车间 | D22: 135358 | E22: 196.4 | F22: 183.5 | G22: 40 | H22: =(E22-F22)*G22 -> 516 | I22: 1.1 | J22: =H22*I22 -> 567.6 | M22: =J22+K22 -> 567.6 | N22: 567.6
A23: 16 | B23: 代家俊 | C23: 车间 | D23: 135380 | E23: 275 | F23: 256.6 | G23: 40 | H23: =(E23-F23)*G23 -> 736 | I23: 1.1 | J23: =H23*I23 -> 809.6 | M23: =J23+K23 -> 809.6 | N23: 809
A24: 17 | B24: 崔汝波 | C24: 车间 | D24: 135376 | E24: 28.2 | F24: 24.2 | G24: 40 | H24: =(E24-F24)*G24 -> 160 | I24: 1.1 | J24: =H24*I24 -> 176 | M24: =J24+K24 -> 176 | N24: 176
A25: 18 | B25: 崔大洪 | C25: 车间 | D25: CJ101 | E25: 430 | F25: 367 | G25: 1 | H25: =(E25-F25)*G25 -> 63 | I25: 1.1 | J25: =H25*I25 -> 69.3 | M25: =J25+K25 -> 69.3 | N25: 69.3
A26: 19 | B26: 崔大云 | C26: 车间 | D26: CJ102 | E26: 1755 | F26: 1491 | G26: 1 | H26: =(E26-F26)*G26 -> 264 | I26: 1.1 | J26: =H26*I26 -> 290.4 | M26: =J26+K26 -> 290.4 | N26: 290.4
A27: 20 | B27: 冯成 | C27: 车间 | D27: 281917 | E27: 48 | F27: 42.1 | G27: 100 | H27: =(E27-F27)*G27 -> 590 | I27: 1.1 | J27: =H27*I27 -> 649 | M27: =J27+K27 -> 649 | N27: 649
A28: 21 | B28: 崔汝义 | C28: 车间 | D28: 136865 | E28: 281 | F28: 267.5 | G28: 20 | H28: =(E28-F28)*G28 -> 270 | I28: 1.1 | J28: =H28*I28 -> 297 | M28: =J28+K28 -> 297 | N28: 297
A29: 22 | B29: 崔文交 | C29: 车间 | D29: 121780 | E29: 50.5 | F29: 45.6 | G29: 20 | H29: =(E29-F29)*G29 -> 98 | I29: 1.1 | J29: =H29*I29 -> 107.8 | M29: =J29+K29 -> 107.8 | N29: 108
A30: 23 | B30: 马世平 | C30: 车间 | D30: 135940 | E30: 37.5 | F30: 33.9 | G30: 30 | H30: =(E30-F30)*G30 -> 108 | I30: 1.1 | J30: =H30*I30 -> 118.8 | M30: =J30+K30 -> 118.8 | N30: 119
A31: 24 | B31: 崔文洪 | C31: 车间 | D31: 121780 | E31: 2536.7 | F31: 2284.3 | G31: 30 | H31: =(E31-F31)*G31 -> 7572 | I31: 1.1 | J31: =H31*I31 -> 8329.2 | M31: =J31+K31 -> 8329.2
A32: 25 | B32: 苏清友 | C32: 车间 | D32: 134768 | E32: 539.6 | F32: 389.7 | G32: 80 | H32: =(E32-F32)*G32 -> 11992 | I32: 1.1 | J32: =H32*I32 -> 13191.2 | M32: =J32+K32 -> 13191.2 | N32: 13191
A33: 26 | B33: 杨文仁 | C33: 车间 | D33: 135939 | E33: 5.2 | F33: 5.2 | G33: 80 | H33: =(E33-F33)*G33 -> 0 | I33: 1.1 | J33: =H33*I33 -> 0 | K33: 457.6 | L33: 上月欠费 | M33: =J33+K33 -> 457.6 | N33: 457.6
A34: 合计： | J34: =SUM(J3:J33) -> 42511.7 | M34: =SUM(M3:M33) -> 42969.3 | N34: =SUM(N3:N33) -> 34635.4
A35: 餐费： | N35: -1905
A36: 报销： | C36: 余波采购李兴平家防雨改造1吨水泥1车沙 | N36: -590
C37: 蒋安坤采购杨文仁家400A空开(二手) | N37: -100
C38: 采购创峰电缆（300*3+150*2）*54米 铝芯电缆+镀锌线鼻子 | N38: -5230
C39: 配电房门改造(活页、锁扣、挂锁) | N39: -34
C40: 购买夜班晚餐方便面 | N40: =-91.9+-65.9 -> -157.8
C41: 6月份电费 | N41: -28797 | O41: 29368.49 | P41: =O41+N41 -> 571.49
C42: 税费 | N42: -85684.86
N43: =N34+SUM(N35:N42) -> -87863.26

Sheet 2025年8月电费
A1: 宏发再生资源市场2025年8月电费收费清单
A2: 序号 | B2: 商户姓名 | C2: 分区 | D2: 电表编号 | E2: 本月电表底数 | F2: 上月电表底数 | G2: 倍率 | H2: 用电量 | I2: 电费单价 | J2: 电费合计 | K2: 补减项 | L2: 备注 | M2: 总计 | N2: 实收
A3: =ROW()-2 -> 1 | B3: 卯声平 | C3: 车间 | D3: 135407 | E3: 1189.3 | F3: 1077.3 | G3: 60 | H3: =(E3-F3)*G3 -> 6720 | I3: 1.1 | J3: =H3*I3 -> 7392 | M3: =J3+J4+K3+K4 -> 8055.3 | N3: 8055
C4: 宿舍 | D4: 222933 | E4: 9245 | F4: 8642 | G4: 1 | H4: =(E4-F4)*G4 -> 603 | I4: 1.1 | J4: =H4*I4 -> 663.3
A5: 2 | B5: 王银全 | C5: 车间 | D5: 135406 | E5: 491.4 | F5: 467.2 | G5: 40 | H5: =(E5-F5)*G5 -> 968 | I5: 1.1 | J5: =H5*I5 -> 1064.8 | M5: =J5+K5 -> 1064.8 | N5: 1064
A6: 3 | B6: 谢贤祥 | C6: 车间 | D6: 135400 | E6: 13.3 | F6: 12.5 | G6: 40 | H6: =(E6-F6)*G6 -> 32 | I6: 1.1 | J6: =H6*I6 -> 35.2 | M6: =J6+J7+K6+K7 -> 160.6 | N6: 160.6
C7: 宿舍 | D7: SS102 | E7: 667 | F7: 553 | G7: 1 | H7: =(E7-F7)*G7 -> 114 | I7: 1.1 | J7: =H7*I7 -> 125.4
A8: 4 | B8: 王银福 | C8: 车间 | D8: 135405 | E8: 388.8 | F8: 362.1 | G8: 40 | H8: =(E8-F8)*G8 -> 1068 | I8: 1.1 | J8: =H8*I8 -> 1174.8 | M8: =J8+K8 -> 1174.8 | N8: 1174.8
A9: 5 | B9: 王文奇 | C9: 车间 | D9: 135401 | E9: 73.9 | F9: 68.6 | G9: 20 | H9: =(E9-F9)*G9 -> 106 | I9: 1.1 | J9: =H9*I9 -> 116.6 | M9: =J9+K9 -> 116.6 | N9: 116.6
A10: 6 | B10: 李兴平 | C10: 车间一 | D10: 135402 | E10: 602.7 | F10: 551.6 | G10: 20 | H10: =(E10-F10)*G10 -> 1022 | I10: 1.1 | J10: =H10*I10 -> 1124.2 | M10: =J10+J11+K10+K11 -> 2048.2 | N10: 2049
C11: 车间二 | D11: 135408 | E11: 244.8 | F11: 223.8 | G11: 40 | H11: =(E11-F11)*G11 -> 840 | I11: 1.1 | J11: =H11*I11 -> 924
A12: 7 | B12: 金耀 | C12: 车间 | D12: 136866 | E12: 234.8 | F12: 222.1 | G12: 20 | H12: =(E12-F12)*G12 -> 254 | I12: 1.1 | J12: =H12*I12 -> 279.4 | M12: =J12+K12 -> 279.4 | N12: 279.4
A13: 8 | B13: 代家超 | C13: 车间 | D13: 135847 | E13: 208.5 | F13: 197.7 | G13: 40 | H13: =(E13-F13)*G13 -> 432 | I13: 1.1 | J13: =H13*I13 -> 475.2 | M13: =J13+K13 -> 475.2 | N13: 475
A14: 9 | B14: 崔宇文 | C14: 车间 | D14: 135848 | E14: 662.5 | F14: 606.2 | G14: 40 | H14: =(E14-F14)*G14 -> 2252 | I14: 1.1 | J14: =H14*I14 -> 2477.2 | M14: =J14+K14 -> 2477.2 | N14: 2477.2
A15: 10 | B15: 崔玉文 | C15: 车间 | D15: 135846 | E15: 630.8 | F15: 579.9 | G15: 40 | H15: =(E15-F15)*G15 -> 2036 | I15: 1.1 | J15: =H15*I15 -> 2239.6 | M15: =J15+K15+J16+K16 -> 2741.2 | N15: 2741
D16: 135379 | E16: 12.1 | F16: 6.4 | G16: 80 | H16: =(E16-F16)*G16 -> 456 | I16: 1.1 | J16: =H16*I16 -> 501.6
A17: 11 | B17: 祖维成 | C17: 车间 | D17: 135845 | E17: 422.2 | F17: 394.2 | G17: 40 | H17: =(E17-F17)*G17 -> 1120 | I17: 1.1 | J17: =H17*I17 -> 1232 | M17: =J17+K17 -> 1232 | N17: 1232
A18: 12 | B18: 崔大冲 | C18: 车间 | D18: 135844 | E18: 54.6 | F18: 48.4 | G18: 30 | H18: =(E18-F18)*G18 -> 186 | I18: 1.1 | J18: =H18*I18 -> 204.6 | M18: =J18+K18 -> 204.6 | N18: 204.6
A19: 13 | B19: 李世坤 | C19: 车间 | D19: 135844 | E19: 66.4 | F19: 54.5 | G19: 30 | H19: =(E19-F19)*G19 -> 357 | I19: 1.1 | J19: =H19*I19 -> 392.7 | M19: =J19+K19 -> 392.7 | N19: 392
A20: 14 | B20: 代家虎 | C20: 车间 | D20: 135850 | E20: 197.1 | F20: 187 | G20: 30 | H20: =(E20-F20)*G20 -> 303 | I20: 1.1 | J20: =H20*I20 -> 333.3 | M20: =J20+K20 -> 333.3 | N20: 333
A21: 15 | B21: 代家鹏 | C21: 车间 | D21: 135358 | E21: 211.7 | F21: 196.4 | G21: 40 | H21: =(E21-F21)*G21 -> 612 | I21: 1.1 | J21: =H21*I21 -> 673.2 | M21: =J21+K21 -> 673.2 | N21: 673.2
A22: 16 | B22: 代家静 | C22: 车间 | D22: 135380 | E22: 295.3 | F22: 275 | G22: 40 | H22: =(E22-F22)*G22 -> 812 | I22: 1.1 | J22: =H22*I22 -> 893.2 | M22: =J22+K22 -> 893.2 | N22: 893
A23: 17 | B23: 崔汝波 | C23: 车间 | D23: 135376 | E23: 32.3 | F23: 28.2 | G23: 40 | H23: =(E23-F23)*G23 -> 164 | I23: 1.1 | J23: =H23*I23 -> 180.4 | M23: =J23+K23 -> 180.4 | N23: 180
A24: 18 | B24: 崔大洪 | C24: 车间 | D24: CJ101 | E24: 496 | F24: 430 | G24: 1 | H24: =(E24-F24)*G24 -> 66 | I24: 1.1 | J24: =H24*I24 -> 72.6 | M24: =J24+K24 -> 72.6 | N24: 72.6
A25: 19 | B25: 崔大云 | C25: 车间 | D25: CJ102 | E25: 2099 | F25: 1755 | G25: 1 | H25: =(E25-F25)*G25 -> 344 | I25: 1.1 | J25: =H25*I25 -> 378.4 | M25: =J25+K25 -> 378.4 | N25: 378.4
A26: 20 | B26: 冯成 | C26: 车间 | D26: 281917 | E26: 56.2 | F26: 48 | G26: 100 | H26: =(E26-F26)*G26 -> 820 | I26: 1.1 | J26: =H26*I26 -> 902 | M26: =J26+K26 -> 902 | N26: 902
A27: 21 | B27: 崔汝义 | C27: 车间 | D27: 136865 | E27: 308.6 | F27: 281 | G27: 20 | H27: =(E27-F27)*G27 -> 552 | I27: 1.1 | J27: =H27*I27 -> 607.2 | M27: =J27+K27 -> 607.2 | N27: 607.2
A28: 22 | B28: 崔文交 | C28: 车间 | D28: 121780 | E28: 62 | F28: 50.5 | G28: 20 | H28: =(E28-F28)*G28 -> 230 | I28: 1.1 | J28: =H28*I28 -> 253 | M28: =J28+K28 -> 253 | N28: 253
A29: 23 | B29: 马世平 | C29: 车间 | D29: 135940 | E29: 41 | F29: 37.5 | G29: 30 | H29: =(E29-F29)*G29 -> 105 | I29: 1.1 | J29: =H29*I29 -> 115.5 | M29: =J29+K29 -> 115.5 | N29: 16
A30: 24 | B30: 崔文洪 | C30: 车间 | D30: 121780 | E30: 2772.3 | F30: 2536.7 | G30: 30 | H30: =(E30-F30)*G30 -> 7068 | I30: 1.1 | J30: =H30*I30 -> 7774.8 | K30: -7774.8 | M30: =J30+K30 -> 1.0004442e-11
A31: 25 | B31: 苏清友 | C31: 车间 | D31: 134768 | E31: 691.1 | F31: 539.6 | G31: 80 | H31: =(E31-F31)*G31 -> 12120 | I31: 1.1 | J31: =H31*I31 -> 13332 | M31: =J31+K31 -> 13332 | N31: 13332
A32: 26 | B32: 杨文仁 | C32: 车间 | D32: 135939 | E32: 32.4 | F32: 5.2 | G32: 80 | H32: =(E32-F32)*G32 -> 2176 | I32: 1.1 | J32: =H32*I32 -> 2393.6 | M32: =J32+K32 -> 2393.6 | N32: 2393.6
A33: 27 | B33: 创峰建材 | C33: 车间 | D33: 施工用电 | E33: 1109 | F33: 256 | G33: 1 | H33: =(E33-F33)*G33 -> 853 | I33: 1.1 | J33: =H33*I33 -> 938.3 | M33: =J33+K33 -> 938.3 | N33: 938
A34: 合计： | J34: =SUM(J3:J32) -> 48331.8 | M34: =SUM(M3:M33) -> 41495.3 | N34: =SUM(N3:N33) -> 41393.2 | O34: =M34-M30 -> 41495.3
A35: 餐费： | N35: -1815
A36: 报销： | C36: 垃圾运费16*380=6080 | N36: -6080
C37: 夜班方便面104.9+65.9+83.9 | N37: =-104.9-65.9-83.9 -> -254.7
C38: 7月电费 | N38: -24324.87
C39: 仓库隔间材料-余波 | N39: -1733
C40: 仓库隔断工钱-余波 | N40: -700
C41: 桶装水-余波 | N41: -70
C42: 环评现场会议接待费（烟、矿泉水）-余波 | N42: -260
C43: 2025-8-20两个杂工拉创峰电缆装电箱-崔送文 | N43: -360
C44: 购买创峰空开-蒋安坤 | N44: -100
C45: 许总电柜钱 | N45: -5000
C46: 王银福更换卷帘门3690+祖维成维修卷帘门换电机 | N46: -4490
A47: 余额： | N47: =N34+SUM(N35:N46) -> -3794.37
N48: -4864

Sheet 2025年9月电费
A1: 宏发再生资源市场2025年9月电费收费清单
A2: 序号 | B2: 商户姓名 | C2: 分区 | D2: 电表编号 | E2: 本月电表底数 | F2: 上月电表底数 | G2: 倍率 | H2: 用电量 | I2: 电费单价 | J2: 电费合计 | K2: 补减项 | L2: 备注 | M2: 总计 | N2: 实收
A3: =ROW()-2 -> 1 | B3: 卯声平 | C3: 车间 | D3: 135407 | E3: 1253.5 | F3: 1189.3 | G3: 60 | H3: =(E3-F3)*G3 -> 3852 | I3: 1.1 | J3: =H3*I3 -> 4237.2 | M3: =J3+J4+K3+K4 -> 4877.4 | N3: 4877.4
C4: 宿舍 | D4: 222933 | E4: 9827 | F4: 9245 | G4: 1 | H4: =(E4-F4)*G4 -> 582 | I4: 1.1 | J4: =H4*I4 -> 640.2
A5: 2 | B5: 王银全 | C5: 车间 | D5: 135406 | E5: 517.5 | F5: 491.4 | G5: 40 | H5: =(E5-F5)*G5 -> 1044 | I5: 1.1 | J5: =H5*I5 -> 1148.4 | M5: =J5+K5 -> 1148.4 | N5: 1148
A6: 3 | B6: 谢贤祥 | C6: 车间 | D6: 135400 | E6: 13.8 | F6: 13.3 | G6: 40 | H6: =(E6-F6)*G6 -> 20 | I6: 1.1 | J6: =H6*I6 -> 22 | M6: =J6+J7+K6+K7 -> 85.8 | N6: 85.8
C7: 宿舍 | D7: SS102 | E7: 725 | F7: 667 | G7: 1 | H7: =(E7-F7)*G7 -> 58 | I7: 1.1 | J7: =H7*I7 -> 63.8
A8: 4 | B8: 王银福 | C8: 车间 | D8: 135405 | E8: 417.2 | F8: 388.8 | G8: 40 | H8: =(E8-F8)*G8 -> 1136 | I8: 1.1 | J8: =H8*I8 -> 1249.6 | M8: =J8+K8 -> 1249.6 | N8: 1249
A9: 5 | B9: 王文奇 | C9: 车间 | D9: 135401 | E9: 78.4 | F9: 73.9 | G9: 20 | H9: =(E9-F9)*G9 -> 90 | I9: 1.1 | J9: =H9*I9 -> 99 | M9: =J9+K9 -> 99 | N9: 99
A10: 6 | B10: 李兴平 | C10: 车间一 | D10: 135402 | E10: 649.9 | F10: 602.7 | G10: 20 | H10: =(E10-F10)*G10 -> 944 | I10: 1.1 | J10: =H10*I10 -> 1038.4 | M10: =J10+J11+K10+K11 -> 1830.4 | N10: 1830
C11: 车间二 | D11: 135408 | E11: 262.8 | F11: 244.8 | G11: 40 | H11: =(E11-F11)*G11 -> 720 | I11: 1.1 | J11: =H11*I11 -> 792
A12: 7 | B12: 金耀 | C12: 车间 | D12: 136866 | E12: 248.7 | F12: 234.8 | G12: 20 | H12: =(E12-F12)*G12 -> 278 | I12: 1.1 | J12: =H12*I12 -> 305.8 | M12: =J12+K12 -> 305.8 | N12: 305.5
A13: 8 | B13: 代家超 | C13: 车间 | D13: 135847 | E13: 218.3 | F13: 208.5 | G13: 40 | H13: =(E13-F13)*G13 -> 392 | I13: 1.1 | J13: =H13*I13 -> 431.2 | M13: =J13+K13 -> 431.2 | N13: 431
A14: 9 | B14: 崔宇文 | C14: 车间 | D14: 135848 | E14: 722.7 | F14: 662.5 | G14: 40 | H14: =(E14-F14)*G14 -> 2408 | I14: 1.1 | J14: =H14*I14 -> 2648.8 | M14: =J14+K14 -> 2648.8 | N14: 2648.8
A15: 10 | B15: 崔玉文 | C15: 车间 | D15: 135846 | E15: 678.9 | F15: 630.8 | G15: 40 | H15: =(E15-F15)*G15 -> 1924 | I15: 1.1 | J15: =H15*I15 -> 2116.4 | M15: =J15+K15+J16+K16 -> 2882 | N15: 2882
D16: 135379 | E16: 20.8 | F16: 12.1 | G16: 80 | H16: =(E16-F16)*G16 -> 696 | I16: 1.1 | J16: =H16*I16 -> 765.6
A17: 11 | B17: 祖维成 | C17: 车间 | D17: 135845 | E17: 448.8 | F17: 422.2 | G17: 40 | H17: =(E17-F17)*G17 -> 1064 | I17: 1.1 | J17: =H17*I17 -> 1170.4 | M17: =J17+K17 -> 1170.4 | N17: 1170
A18: 12 | B18: 崔大冲 | C18: 车间 | D18: 135844 | E18: 62.3 | F18: 54.6 | G18: 30 | H18: =(E18-F18)*G18 -> 231 | I18: 1.1 | J18: =H18*I18 -> 254.1 | M18: =J18+K18 -> 254.1 | N18: 254.1
A19: 13 | B19: 李世坤 | C19: 车间 | D19: 135844 | E19: 77.5 | F19: 66.4 | G19: 30 | H19: =(E19-F19)*G19 -> 333 | I19: 1.1 | J19: =H19*I19 -> 366.3 | M19: =J19+K19 -> 366.3 | N19: 366.3
A20: 14 | B20: 代家虎 | C20: 车间 | D20: 135850 | E20: 207 | F20: 197.1 | G20: 30 | H20: =(E20-F20)*G20 -> 297 | I20: 1.1 | J20: =H20*I20 -> 326.7 | M20: =J20+K20 -> 326.7 | N20: 326
A21: 15 | B21: 代家鹏 | C21: 车间 | D21: 135358 | E21: 222.4 | F21: 211.7 | G21: 40 | H21: =(E21-F21)*G21 -> 428 | I21: 1.1 | J21: =H21*I21 -> 470.8 | M21: =J21+K21 -> 470.8 | N21: 470
A22: 16 | B22: 代家静 | C22: 车间 | D22: 135380 | E22: 311.4 | F22: 295.3 | G22: 40 | H22: =(E22-F22)*G22 -> 644 | I22: 1.1 | J22: =H22*I22 -> 708.4 | M22: =J22+K22 -> 708.4 | N22: 708
A23: 17 | B23: 崔汝波 | C23: 车间 | D23: 135376 | E23: 36.7 | F23: 32.3 | G23: 40 | H23: =(E23-F23)*G23 -> 176 | I23: 1.1 | J23: =H23*I23 -> 193.6 | M23: =J23+K23 -> 193.6 | N23: 194
A24: 18 | B24: 崔大洪 | C24: 车间 | D24: CJ101 | E24: 561 | F24: 496 | G24: 1 | H24: =(E24-F24)*G24 -> 65 | I24: 1.1 | J24: =H24*I24 -> 71.5 | M24: =J24+K24 -> 71.5 | N24: 71.5
A25: 19 | B25: 崔大云 | C25: 车间 | D25: CJ102 | E25: 2494 | F25: 2099 | G25: 1 | H25: =(E25-F25)*G25 -> 395 | I25: 1.1 | J25: =H25*I25 -> 434.5 | M25: =J25+K25 -> 434.5 | N25: 434.5
A26: 20 | B26: 冯成 | C26: 车间 | D26: 281917 | E26: 68 | F26: 56.2 | G26: 100 | H26: =(E26-F26)*G26 -> 1180 | I26: 1.1 | J26: =H26*I26 -> 1298 | M26: =J26+K26 -> 1298 | N26: 1298
A27: 21 | B27: 崔汝义 | C27: 车间 | D27: 136865 | E27: 327 | F27: 308.6 | G27: 20 | H27: =(E27-F27)*G27 -> 368 | I27: 1.1 | J27: =H27*I27 -> 404.8 | M27: =J27+K27 -> 404.8 | N27: 404
A28: 22 | B28: 崔文交 | C28: 车间 | D28: 121780 | E28: 70 | F28: 62 | G28: 20 | H28: =(E28-F28)*G28 -> 160 | I28: 1.1 | J28: =H28*I28 -> 176 | M28: =J28+K28 -> 176 | N28: 176
A29: 23 | B29: 马世平 | C29: 车间 | D29: 135940 | E29: 44.7 | F29: 41 | G29: 30 | H29: =(E29-F29)*G29 -> 111 | I29: 1.1 | J29: =H29*I29 -> 122.1 | M29: =J29+K29 -> 122.1 | N29: 123
A30: 24 | B30: 崔文洪 | C30: 车间 | D30: 121780 | E30: 2997.5 | F30: 2772.3 | G30: 30 | H30: =(E30-F30)*G30 -> 6756 | I30: 1.1 | J30: =H30*I30 -> 7431.6 | M30: 0
A31: 25 | B31: 苏清友 | C31: 车间 | D31: 134768 | E31: 839.3 | F31: 691.1 | G31: 80 | H31: =(E31-F31)*G31 -> 11856 | I31: 1.1 | J31: =H31*I31 -> 13041.6 | M31: =J31+K31 -> 13041.6 | N31: 13041
A32: 26 | B32: 杨文仁 | C32: 车间 | D32: 135939 | E32: 66.4 | F32: 32.4 | G32: 80 | H32: =(E32-F32)*G32 -> 2720 | I32: 1.1 | J32: =H32*I32 -> 2992 | M32: =J32+K32 -> 2992 | N32: 2992
A33: 27 | B33: 创峰建材 | C33: 车间 | D33: 施工用电 | E33: 17.1 | F33: 0 | G33: 80 | H33: =(E33-F33)*G33 -> 1368 | I33: 1.1 | J33: =H33*I33 -> 1504.8 | M33: =J33+K33 -> 1504.8 | N33: 1504.8 | O33: =N33-M33 -> 0
A34: 合计： | J34: =SUM(J3:J33) -> 46525.6 | M34: =SUM(M3:M33) -> 39094 | N34: =SUM(N3:N33) -> 39089.7 | O34: =M34-M30 -> 39094
A35: 餐费： | N35: -1980
A36: 报销： | C36: 崔文洪挖机装垃圾工钱 | N36: -2000
C37: 桶装水10桶*7元 | N37: -70
C38: 8月代缴电费 | N38: -29977.06
C39: 全铜并沟线夹*5（李兴平改造用） | N39: -75.65
C40: 冯成彩钢瓦维修工钱 | N40: -600
C41: 冯成彩钢瓦维修租用升高车 | N41: -300
C42: 李兴平门口场地清理、树坑、厂区道路混凝土修复：杂工钱2人*180元*2天 | N42: -720
C43: 宽带充值 | N43: -1000
C44: 值班晚饭方便食品62.9+52.9 | N44: =-62.9-52.9 -> -115.8
C45: 杨文仁：磨机房用电改造电缆电线及配件 | N45: -3079.5
A47: 余额： | N47: =N34+SUM(N35:N46) -> -828.31

Sheet 2025年10月电费
A1: 宏发再生资源市场2025年10月电费收费清单
A2: 序号 | B2: 商户姓名 | C2: 分区 | D2: 电表编号 | E2: 本月电表底数 | F2: 上月电表底数 | G2: 倍率 | H2: 用电量 | I2: 电费单价 | J2: 电费合计 | K2: 补减项 | L2: 备注 | M2: 总计 | N2: 实收
A3: =ROW()-2 -> 1 | B3: 卯声平 | C3: 车间 | D3: 135407 | E3: 1319.7 | F3: 1253.5 | G3: 60 | H3: =(E3-F3)*G3 -> 3972 | I3: 1.1 | J3: =H3*I3 -> 4369.2 | M3: =J3+J4+K3+K4 -> 4999.5 | N3: 5000
C4: 宿舍 | D4: 222933 | E4: 10400 | F4: 9827 | G4: 1 | H4: =(E4-F4)*G4 -> 573 | I4: 1.1 | J4: =H4*I4 -> 630.3
A5: 2 | B5: 王银全 | C5: 车间 | D5: 135406 | E5: 539.3 | F5: 517.5 | G5: 40 | H5: =(E5-F5)*G5 -> 872 | I5: 1.1 | J5: =H5*I5 -> 959.2 | M5: =J5+K5 -> 959.2 | N5: 959
A6: 3 | B6: 谢贤祥 | C6: 车间 | D6: 135400 | E6: 14.3 | F6: 13.8 | G6: 40 | H6: =(E6-F6)*G6 -> 20 | I6: 1.1 | J6: =H6*I6 -> 22 | M6: =J6+J7+K6+K7 -> 73.7 | N6: 73.7
C7: 宿舍 | D7: SS102 | E7: 772 | F7: 725 | G7: 1 | H7: =(E7-F7)*G7 -> 47 | I7: 1.1 | J7: =H7*I7 -> 51.7
A8: 4 | B8: 王银福 | C8: 车间 | D8: 135405 | E8: 441 | F8: 417.2 | G8: 40 | H8: =(E8-F8)*G8 -> 952 | I8: 1.1 | J8: =H8*I8 -> 1047.2 | M8: =J8+K8 -> 1047.2 | N8: 1047
A9: 5 | B9: 王文奇 | C9: 车间 | D9: 135401 | E9: 84.4 | F9: 78.4 | G9: 20 | H9: =(E9-F9)*G9 -> 120 | I9: 1.1 | J9: =H9*I9 -> 132 | M9: =J9+K9 -> 132 | N9: 132
A10: 6 | B10: 李兴平 | C10: 车间一 | D10: 135402 | E10: 697.7 | F10: 649.9 | G10: 20 | H10: =(E10-F10)*G10 -> 956 | I10: 1.1 | J10: =H10*I10 -> 1051.6 | M10: =J10+J11+K10+K11 -> 1786.4 | N10: 1786
C11: 车间二 | D11: 135408 | E11: 279.5 | F11: 262.8 | G11: 40 | H11: =(E11-F11)*G11 -> 668 | I11: 1.1 | J11: =H11*I11 -> 734.8
A12: 7 | B12: 金耀 | C12: 车间 | D12: 136866 | E12: 258.1 | F12: 248.7 | G12: 20 | H12: =(E12-F12)*G12 -> 188 | I12: 1.1 | J12: =H12*I12 -> 206.8 | M12: =J12+K12 -> 206.8 | N12: 207
A13: 8 | B13: 代家超 | C13: 车间 | D13: 135847 | E13: 226.5 | F13: 218.3 | G13: 40 | H13: =(E13-F13)*G13 -> 328 | I13: 1.1 | J13: =H13*I13 -> 360.8 | M13: =J13+K13 -> 360.8 | N13: 360
A14: 9 | B14: 崔宇文 | C14: 车间 | D14: 135848 | E14: 783.2 | F14: 722.7 | G14: 40 | H14: =(E14-F14)*G14 -> 2420 | I14: 1.1 | J14: =H14*I14 -> 2662 | M14: =J14+K14 -> 2662 | N14: 2662
A15: 10 | B15: 崔玉文 | C15: 车间 | D15: 135846 | E15: 721.1 | F15: 678.9 | G15: 40 | H15: =(E15-F15)*G15 -> 1688 | I15: 1.1 | J15: =H15*I15 -> 1856.8 | M15: =J15+K15+J16+K16 -> 2200 | N15: 2200
D16: 135379 | E16: 24.7 | F16: 20.8 | G16: 80 | H16: =(E16-F16)*G16 -> 312 | I16: 1.1 | J16: =H16*I16 -> 343.2
A17: 11 | B17: 祖维成 | C17: 车间 | D17: 135845 | E17: 476.5 | F17: 448.8 | G17: 40 | H17: =(E17-F17)*G17 -> 1108 | I17: 1.1 | J17: =H17*I17 -> 1218.8 | M17: =J17+K17 -> 1218.8 | N17: 1218
A18: 12 | B18: 崔大冲 | C18: 车间 | D18: 135844 | E18: 68.2 | F18: 62.3 | G18: 30 | H18: =(E18-F18)*G18 -> 177 | I18: 1.1 | J18: =H18*I18 -> 194.7 | M18: =J18+K18 -> 194.7 | N18: 194.7
A19: 13 | B19: 李世坤 | C19: 车间 | D19: 135844 | E19: 85.6 | F19: 77.5 | G19: 30 | H19: =(E19-F19)*G19 -> 243 | I19: 1.1 | J19: =H19*I19 -> 267.3 | M19: =J19+K19 -> 267.3 | N19: 267.3
A20: 14 | B20: 代家虎 | C20: 车间 | D20: 135850 | E20: 215.3 | F20: 207 | G20: 30 | H20: =(E20-F20)*G20 -> 249 | I20: 1.1 | J20: =H20*I20 -> 273.9 | M20: =J20+K20 -> 273.9 | N20: 273
A21: 15 | B21: 代家鹏 | C21: 车间 | D21: 135358 | E21: 233.3 | F21: 222.4 | G21: 40 | H21: =(E21-F21)*G21 -> 436 | I21: 1.1 | J21: =H21*I21 -> 479.6 | M21: =J21+K21 -> 479.6 | N21: 479.6
A22: 16 | B22: 代家静 | C22: 车间 | D22: 135380 | E22: 332.1 | F22: 311.4 | G22: 40 | H22: =(E22-F22)*G22 -> 828 | I22: 1.1 | J22: =H22*I22 -> 910.8 | M22: =J22+K22 -> 910.8 | N22: 910
A23: 17 | B23: 崔汝波 | C23: 车间 | D23: 135376 | E23: 39.6 | F23: 36.7 | G23: 40 | H23: =(E23-F23)*G23 -> 116 | I23: 1.1 | J23: =H23*I23 -> 127.6 | M23: =J23+K23 -> 127.6 | N23: 128
A24: 18 | B24: 崔大洪 | C24: 车间 | D24: CJ101 | E24: 617 | F24: 561 | G24: 1 | H24: =(E24-F24)*G24 -> 56 | I24: 1.1 | J24: =H24*I24 -> 61.6 | M24: =J24+K24 -> 61.6 | N24: 61.6
A25: 19 | B25: 崔大云 | C25: 车间 | D25: CJ102 | E25: 2750 | F25: 2494 | G25: 1 | H25: =(E25-F25)*G25 -> 256 | I25: 1.1 | J25: =H25*I25 -> 281.6 | M25: =J25+K25 -> 281.6 | N25: 281.6
A26: 20 | B26: 冯成 | C26: 车间 | D26: 281917 | E26: 77.8 | F26: 68 | G26: 100 | H26: =(E26-F26)*G26 -> 980 | I26: 1.1 | J26: =H26*I26 -> 1078 | M26: =J26+K26 -> 1078 | N26: 1078
A27: 21 | B27: 崔汝义 | C27: 车间 | D27: 136865 | E27: 343.6 | F27: 327 | G27: 20 | H27: =(E27-F27)*G27 -> 332 | I27: 1.1 | J27: =H27*I27 -> 365.2 | M27: =J27+K27 -> 365.2 | N27: 365.2
A28: 22 | B28: 崔文交 | C28: 车间 | D28: 121780 | E28: 76.7 | F28: 70 | G28: 20 | H28: =(E28-F28)*G28 -> 134 | I28: 1.1 | J28: =H28*I28 -> 147.4 | M28: =J28+K28 -> 147.4 | N28: 148
A29: 23 | B29: 马世平 | C29: 车间 | D29: 135940 | E29: 49.6 | F29: 44.7 | G29: 30 | H29: =(E29-F29)*G29 -> 147 | I29: 1.1 | J29: =H29*I29 -> 161.7 | M29: =J29+K29 -> 161.7 | N29: 162
A30: 24 | B30: 崔文洪 | C30: 车间 | D30: 121780 | E30: 3253.7 | F30: 2997.5 | G30: 30 | H30: =(E30-F30)*G30 -> 7686 | I30: 1.1 | J30: =H30*I30 -> 8454.6 | M30: 0
A31: 25 | B31: 苏清友 | C31: 车间 | D31: 134768 | E31: 938.3 | F31: 839.3 | G31: 80 | H31: =(E31-F31)*G31 -> 7920 | I31: 1.1 | J31: =H31*I31 -> 8712 | M31: =J31+K31 -> 8712 | N31: 8712
A32: 26 | B32: 杨文仁 | C32: 宿舍 | E32: 24 | F32: 0 | G32: 1 | H32: =(E32-F32)*G32 -> 24 | I32: 1.1 | J32: 26.4 | K32: 12 | L32: 水费12元 | M32: =J32+K32+J33+K33 -> 4165.6 | N32: 4165.6
A33: 27 | C33: 车间 | D33: 135939 | E33: 113.3 | F33: 66.4 | G33: 80 | H33: =(E33-F33)*G33 -> 3752 | I33: 1.1 | J33: =H33*I33 -> 4127.2
A34: 28 | B34: 创峰建材 | C34: 车间 | D34: 施工用电 | E34: 39.4 | F34: 17.1 | G34: 80 | H34: =(E34-F34)*G34 -> 1784 | I34: 1.1 | J34: =H34*I34 -> 1962.4 | M34: =J34+K34 -> 1962.4 | N34: 1962 | O34: =N34-M34 -> -0.4
A35: 合计： | J35: =SUM(J3:J34) -> 43278.4 | M35: =SUM(M3:M34) -> 34835.8 | N35: =SUM(N3:N34) -> 34833.3 | O35: =M35-M30 -> 34835.8
A36: 餐费： | N36: -1895
A37: 报销： | C37: 购买中性笔20支*2盒 | N37: -34.7
C38: 桶装水10桶*7元 | N38: -70
C39: 9月代缴电费 | N39: -27310.52
C40: 取暖炉桌垫 | N40: -20 | P40: 冯成彩钢瓦维修
C41: 保洁申购橡胶手套*10 | N41: -40.62
C42: 卷帘门遥控器电池A23 12V 15粒 | N42: -35.51
C43: 双头监控摄像头 | N43: -360
C44: 许总家零散配件(互感器、线鼻子等：杨文仁及创峰) | N44: -471
C45: 磅房监控用无线鼠标 | N45: -24.9
C46: 上月电费结转 | N46: ='2025年9月电费'!N47 -> -828.31
C47: 夜班方便食品（方便米饭*18） | N47: -188.84
A48: 余额： | N48: =N35+SUM(N36:N47) -> 3553.9

Sheet 2025年11月电费
A1: 宏发再生资源市场2025年11月电费收费清单
A2: 序号 | B2: 商户姓名 | C2: 分区 | D2: 电表编号 | E2: 本月电表底数 | F2: 上月电表底数 | G2: 倍率 | H2: 用电量 | I2: 电费单价 | J2: 电费合计 | K2: 补减项 | L2: 备注 | M2: 总计 | N2: 实收
A3: =ROW()-2 -> 1 | B3: 卯声平 | C3: 车间 | D3: 135407 | E3: 1398.9 | F3: 1319.7 | G3: 60 | H3: =(E3-F3)*G3 -> 4752 | I3: 1.1 | J3: =H3*I3 -> 5227.2 | M3: =J3+J4+K3+K4 -> 6619.8 | N3: 6620
C4: 宿舍 | D4: 222933 | E4: 11666 | F4: 10400 | G4: 1 | H4: =(E4-F4)*G4 -> 1266 | I4: 1.1 | J4: =H4*I4 -> 1392.6
A5: 2 | B5: 王银全 | C5: 车间 | D5: 135406 | E5: 579.7 | F5: 539.3 | G5: 40 | H5: =(E5-F5)*G5 -> 1616 | I5: 1.1 | J5: =H5*I5 -> 1777.6 | M5: =J5+K5 -> 1777.6 | N5: 1777
A6: 3 | B6: 谢贤祥 | C6: 车间 | D6: 135400 | E6: 15 | F6: 14.3 | G6: 40 | H6: =(E6-F6)*G6 -> 28 | I6: 1.1 | J6: =H6*I6 -> 30.8 | M6: =J6+J7+K6+K7 -> 108.9 | N6: 108.9
C7: 宿舍 | D7: SS102 | E7: 843 | F7: 772 | G7: 1 | H7: =(E7-F7)*G7 -> 71 | I7: 1.1 | J7: =H7*I7 -> 78.1
A8: 4 | B8: 王银福 | C8: 车间 | D8: 135405 | E8: 474.7 | F8: 441 | G8: 40 | H8: =(E8-F8)*G8 -> 1348 | I8: 1.1 | J8: =H8*I8 -> 1482.8 | M8: =J8+K8 -> 1482.8 | N8: 1482
A9: 5 | B9: 王文奇 | C9: 车间 | D9: 135401 | E9: 92.7 | F9: 84.4 | G9: 20 | H9: =(E9-F9)*G9 -> 166 | I9: 1.1 | J9: =H9*I9 -> 182.6 | M9: =J9+K9 -> 182.6 | N9: 182.6
A10: 6 | B10: 李兴平 | C10: 车间一 | D10: 135402 | E10: 750.1 | F10: 697.7 | G10: 20 | H10: =(E10-F10)*G10 -> 1048 | I10: 1.1 | J10: =H10*I10 -> 1152.8 | M10: =J10+J11+K10+K11+J12+K12 -> 2393.6 | N10: 2393.6
C11: 车间二 | D11: 135408 | E11: 302.4 | F11: 279.5 | G11: 40 | H11: =(E11-F11)*G11 -> 916 | I11: 1.1 | J11: =H11*I11 -> 1007.6
C12: 车间三 | D12: 120279 | E12: 5.3 | F12: 0 | G12: 40 | H12: =(E12-F12)*G12 -> 212 | I12: 1.1 | J12: =H12*I12 -> 233.2
A13: 7 | B13: 金耀 | C13: 车间 | D13: 136866 | E13: 264.7 | F13: 258.1 | G13: 20 | H13: =(E13-F13)*G13 -> 132 | I13: 1.1 | J13: =H13*I13 -> 145.2 | M13: =J13+K13 -> 145.2 | N13: 145.2
A14: 8 | B14: 代家超 | C14: 车间 | D14: 135847 | E14: 239.5 | F14: 226.5 | G14: 40 | H14: =(E14-F14)*G14 -> 520 | I14: 1.1 | J14: =H14*I14 -> 572 | M14: =J14+K14 -> 572 | N14: 572
A15: 9 | B15: 崔宇文 | C15: 车间 | D15: 135848 | E15: 844 | F15: 783.2 | G15: 40 | H15: =(E15-F15)*G15 -> 2432 | I15: 1.1 | J15: =H15*I15 -> 2675.2 | M15: =J15+K15 -> 2675.2 | N15: 2675.2
A16: 10 | B16: 崔玉文 | C16: 车间 | D16: 135846 | E16: 768.8 | F16: 721.1 | G16: 40 | H16: =(E16-F16)*G16 -> 1908 | I16: 1.1 | J16: =H16*I16 -> 2098.8 | M16: =J16+K16+J17+K17 -> 3885.2 | N16: 3885
D17: 135379 | E17: 45 | F17: 24.7 | G17: 80 | H17: =(E17-F17)*G17 -> 1624 | I17: 1.1 | J17: =H17*I17 -> 1786.4
A18: 11 | B18: 祖维成 | C18: 车间 | D18: 135845 | E18: 514.6 | F18: 476.5 | G18: 40 | H18: =(E18-F18)*G18 -> 1524 | I18: 1.1 | J18: =H18*I18 -> 1676.4 | M18: =J18+K18 -> 1676.4 | N18: 1676
A19: 12 | B19: 崔大冲 | C19: 车间 | D19: 135844 | E19: 75.2 | F19: 68.2 | G19: 30 | H19: =(E19-F19)*G19 -> 210 | I19: 1.1 | J19: =H19*I19 -> 231 | M19: =J19+K19 -> 231 | N19: 231
A20: 13 | B20: 李世坤 | C20: 车间 | D20: 135844 | E20: 96.8 | F20: 85.6 | G20: 30 | H20: =(E20-F20)*G20 -> 336 | I20: 1.1 | J20: =H20*I20 -> 369.6 | M20: =J20+K20 -> 369.6 | N20: 369.6
A21: 14 | B21: 代家虎 | C21: 车间 | D21: 135850 | E21: 223.9 | F21: 215.3 | G21: 30 | H21: =(E21-F21)*G21 -> 258 | I21: 1.1 | J21: =H21*I21 -> 283.8 | M21: =J21+K21 -> 283.8 | N21: 283
A22: 15 | B22: 代家鹏 | C22: 车间 | D22: 135358 | E22: 247.9 | F22: 233.3 | G22: 40 | H22: =(E22-F22)*G22 -> 584 | I22: 1.1 | J22: =H22*I22 -> 642.4 | M22: =J22+K22 -> 642.4 | N22: 642
A23: 16 | B23: 代家静 | C23: 车间 | D23: 135380 | E23: 354.3 | F23: 332.1 | G23: 40 | H23: =(E23-F23)*G23 -> 888 | I23: 1.1 | J23: =H23*I23 -> 976.8 | M23: =J23+K23 -> 976.8 | N23: 976
A24: 17 | B24: 崔汝波 | C24: 车间 | D24: 135376 | E24: 41.7 | F24: 39.6 | G24: 40 | H24: =(E24-F24)*G24 -> 84 | I24: 1.1 | J24: =H24*I24 -> 92.4 | M24: =J24+K24 -> 92.4 | N24: 93
A25: 18 | B25: 崔大洪 | C25: 车间 | D25: CJ101 | E25: 676 | F25: 617 | G25: 1 | H25: =(E25-F25)*G25 -> 59 | I25: 1.1 | J25: =H25*I25 -> 64.9 | M25: =J25+K25 -> 64.9 | N25: 65
A26: 19 | B26: 崔大云 | C26: 车间 | D26: CJ102 | E26: 3040 | F26: 2750 | G26: 1 | H26: =(E26-F26)*G26 -> 290 | I26: 1.1 | J26: =H26*I26 -> 319 | M26: =J26+K26 -> 319 | N26: 319
A27: 20 | B27: 冯成 | C27: 车间 | D27: 281917 | E27: 92.1 | F27: 77.8 | G27: 100 | H27: =(E27-F27)*G27 -> 1430 | I27: 1.1 | J27: =H27*I27 -> 1573 | M27: =J27+K27 -> 1573 | N27: 1573
A28: 21 | B28: 崔汝义 | C28: 车间 | D28: 136865 | E28: 359 | F28: 343.6 | G28: 20 | H28: =(E28-F28)*G28 -> 308 | I28: 1.1 | J28: =H28*I28 -> 338.8 | M28: =J28+K28 -> 338.8 | N28: 338.8
A29: 22 | B29: 崔文交 | C29: 车间 | D29: 121780 | E29: 82.9 | F29: 76.7 | G29: 20 | H29: =(E29-F29)*G29 -> 124 | I29: 1.1 | J29: =H29*I29 -> 136.4 | M29: =J29+K29 -> 136.4 | N29: 137
A30: 23 | B30: 马世平 | C30: 车间 | D30: 135940 | E30: 55.7 | F30: 49.6 | G30: 30 | H30: =(E30-F30)*G30 -> 183 | I30: 1.1 | J30: =H30*I30 -> 201.3 | M30: =J30+K30 -> 201.3 | N30: 202
A31: 24 | B31: 崔文洪 | C31: 车间 | D31: 121780 | E31: 3497.2 | F31: 3253.7 | G31: 30 | H31: =(E31-F31)*G31 -> 7305 | I31: 1.1 | J31: =H31*I31 -> 8035.5 | M31: 0 | N31: 0
A32: 25 | B32: 苏清友 | C32: 车间 | D32: 134768 | E32: 970.5 | F32: 938.3 | G32: 80 | H32: =(E32-F32)*G32 -> 2576 | I32: 1.1 | J32: =H32*I32 -> 2833.6 | M32: =J32+K32 -> 2833.6 | N32: 2833
A33: 27 | B33: 杨文仁 | C33: 车间 | D33: 135939 | E33: 161.6 | F33: 113.3 | G33: 80 | H33: =(E33-F33)*G33 -> 3864 | I33: 1.1 | J33: =H33*I33 -> 4250.4 | M33: =J33+K33 -> 4250.4 | N33: 4251
A34: 28 | B34: 创峰建材 | C34: 车间 | D34: 施工用电 | E34: 86.8 | F34: 39.4 | G34: 80 | H34: =(E34-F34)*G34 -> 3792 | I34: 1.1 | J34: =H34*I34 -> 4171.2 | M34: =J34+K34 -> 4171.2 | N34: 4171.2
A35: . | H35: =SUM(H3:H34) -> 41854 | J35: =SUM(J3:J34) -> 46039.4 | M35: =SUM(M3:M34) -> 38003.9 | N35: =SUM(N3:N34) -> 38002.1 | O35: =M35-N35 -> 1.8 | P35: =M35/H35 -> 0.90801118
A36: 餐费： | N36: -1967
A37: 报销： | C37: 2025-12-13 挖机驾驶员工资 | N37: -300
C38: 2025-12-12 挖机驾驶员工资 | N38: -400
C39: 2025-12-10 挖机驾驶员工资 | N39: -300
C40: 10月代缴电费 | N40: -27535.31
C41: 夜班方便食品（康师傅拌面*12+方便米饭*12盒） | N41: =-69.74*2-49.74 -> -189.22
C42: 2025-12-11 挖机驾驶员路费 | N42: -100
C43: 2025-12-23 挖机驾驶员工资 | N43: -300
C44: 6条中支金腰带 270*6 | N44: =-6*270 -> -1620
C45: 1497.6吨*4元 | N45: -5990
C46: 桶装水7元*13桶 | N46: =-7*13 -> -91
C47: 2025-12-27 挖机驾驶员工资 | N47: -300
C48: 上月结转 | N48: ='2025年10月电费'!N48 -> 3553.9
A49: 余额： | N49: =N35+SUM(N36:N48) -> 2463.47
A50: 筛网用圆钢3300元*0.774吨+100元运费 | N50: =3300*0.774+100 -> 2654.2
A51: 拉灰运费1497.6*7 | N51: =1949.6*7 -> 13647.2

Sheet 2025年12月电费
A1: 宏发再生资源市场2025年12月电费收费清单
A2: 序号 | B2: 商户姓名 | C2: 分区 | D2: 电表编号 | E2: 本月电表底数 | F2: 上月电表底数 | G2: 倍率 | H2: 用电量 | I2: 单价 | J2: 电费合计_ | K2: 电费合计 | L2: 补减项 | M2: 备注 | N2: 总计 | O2: 实收_
A3: =ROW()-2 -> 1 | B3: 卯声平 | C3: 车间 | D3: 135407 | E3: 1507.4 | F3: 1398.9 | G3: 60 | H3: =(E3-F3)*G3 -> 6510 | I3: 1.1 | J3: =H3*I3 -> 7161 | K3: =(E3-F3)*G3*I3 -> 7161 | N3: =K3+K4 -> 8994.7 | O3: 8994
C4: 宿舍 | D4: 222933 | E4: 13333 | F4: 11666 | G4: 1 | H4: =(E4-F4)*G4 -> 1667 | I4: 1.1 | J4: =H4*I4 -> 1833.7 | K4: =(E4-F4)*G4*I4 -> 1833.7
A5: 2 | B5: 王银全 | C5: 车间 | D5: 135406 | E5: 620.2 | F5: 579.7 | G5: 40 | H5: =(E5-F5)*G5 -> 1620 | I5: 1.1 | J5: =H5*I5 -> 1782 | K5: =(E5-F5)*G5*I5 -> 1782 | N5: =K5 -> 1782 | O5: 1782
A6: 3 | B6: 谢贤祥 | C6: 车间 | D6: 135400 | E6: 15.5 | F6: 15 | G6: 40 | H6: =(E6-F6)*G6 -> 20 | I6: 1.1 | J6: =H6*I6 -> 22 | K6: =(E6-F6)*G6*I6 -> 22 | N6: =K6+K7 -> 90.2 | O6: 90
C7: 宿舍 | D7: 无 | E7: 905 | F7: 843 | G7: 1 | H7: =(E7-F7)*G7 -> 62 | I7: 1.1 | J7: =H7*I7 -> 68.2 | K7: =(E7-F7)*G7*I7 -> 68.2
A8: 4 | B8: 王银福 | C8: 车间 | D8: 135405 | E8: 514 | F8: 474.7 | G8: 40 | H8: =(E8-F8)*G8 -> 1572 | I8: 1.1 | J8: =H8*I8 -> 1729.2 | K8: =(E8-F8)*G8*I8 -> 1729.2 | N8: =K8+K9 -> 1914 | O8: 1914
C9: 宿舍 | D9: 无 | E9: 168 | F9: 0 | G9: 1 | H9: =(E9-F9)*G9 -> 168 | I9: 1.1 | J9: =H9*I9 -> 184.8 | K9: =(E9-F9)*G9*I9 -> 184.8
A10: 5 | B10: 王文奇 | C10: 车间 | D10: 135401 | E10: 99.5 | F10: 92.7 | G10: 20 | H10: =(E10-F10)*G10 -> 136 | I10: 1.1 | J10: =H10*I10 -> 149.6 | K10: =(E10-F10)*G10*I10 -> 149.6 | N10: =K10 -> 149.6 | O10: 150
A11: 6 | B11: 李兴平 | C11: 车间一 | D11: 135402 | E11: 826.1 | F11: 750.1 | G11: 20 | H11: =(E11-F11)*G11 -> 1520 | I11: 1.1 | J11: =H11*I11 -> 1672 | K11: =(E11-F11)*G11*I11 -> 1672 | N11: =K11+K12+K13 -> 2846.8 | O11: 2846.8
C12: 车间二 | D12: 135408 | E12: 319.8 | F12: 302.4 | G12: 40 | H12: =(E12-F12)*G12 -> 696 | I12: 1.1 | J12: =H12*I12 -> 765.6 | K12: =(E12-F12)*G12*I12 -> 765.6
C13: 车间三 | D13: 120279 | E13: 14.6 | F13: 5.3 | G13: 40 | H13: =(E13-F13)*G13 -> 372 | I13: 1.1 | J13: =H13*I13 -> 409.2 | K13: =(E13-F13)*G13*I13 -> 409.2
A14: 7 | B14: 金耀 | C14: 车间 | D14: 136866 | E14: 276.4 | F14: 264.7 | G14: 20 | H14: =(E14-F14)*G14 -> 234 | I14: 1.1 | J14: =H14*I14 -> 257.4 | K14: =(E14-F14)*G14*I14 -> 257.4 | N14: =K14 -> 257.4 | O14: 257
A15: 8 | B15: 代家超 | C15: 车间 | D15: 135847 | E15: 260.4 | F15: 239.5 | G15: 40 | H15: =(E15-F15)*G15 -> 836 | I15: 1.1 | J15: =H15*I15 -> 919.6 | K15: =(E15-F15)*G15*I15 -> 919.6 | N15: =K15 -> 919.6 | O15: 919
A16: 9 | B16: 崔宇文 | C16: 车间 | D16: 135848 | E16: 913.3 | F16: 844 | G16: 40 | H16: =(E16-F16)*G16 -> 2772 | I16: 1.1 | J16: =H16*I16 -> 3049.2 | K16: =(E16-F16)*G16*I16 -> 3049.2 | N16: =K16 -> 3049.2 | O16: 3049.2
A17: 10 | B17: 崔玉文 | C17: 车间 | D17: 135846 | E17: 824.8 | F17: 768.8 | G17: 40 | H17: =(E17-F17)*G17 -> 2240 | I17: 1.1 | J17: =H17*I17 -> 2464 | K17: =(E17-F17)*G17*I17 -> 2464 | N17: =K17+K18 -> 3476 | O17: 3476
D18: 135379 | E18: 56.5 | F18: 45 | G18: 80 | H18: =(E18-F18)*G18 -> 920 | I18: 1.1 | J18: =H18*I18 -> 1012 | K18: =(E18-F18)*G18*I18 -> 1012
A19: 11 | B19: 祖维成 | C19: 车间 | D19: 135845 | E19: 554.6 | F19: 514.6 | G19: 40 | H19: =(E19-F19)*G19 -> 1600 | I19: 1.1 | J19: =H19*I19 -> 1760 | K19: =(E19-F19)*G19*I19 -> 1760 | N19: =K19 -> 1760 | O19: 1760
A20: 12 | B20: 崔大冲 | C20: 车间 | D20: 135844 | E20: 83.5 | F20: 75.2 | G20: 30 | H20: =(E20-F20)*G20 -> 249 | I20: 1.1 | J20: =H20*I20 -> 273.9 | K20: =(E20-F20)*G20*I20 -> 273.9 | N20: =K20 -> 273.9 | O20: 273
A21: 13 | B21: 李世坤 | C21: 车间 | D21: 135844 | E21: 107.8 | F21: 96.8 | G21: 30 | H21: =(E21-F21)*G21 -> 330 | I21: 1.1 | J21: =H21*I21 -> 363 | K21: =(E21-F21)*G21*I21 -> 363 | N21: =K21 -> 363 | O21: 363
A22: 14 | B22: 代家虎 | C22: 车间 | D22: 135850 | E22: 237.7 | F22: 223.9 | G22: 30 | H22: =(E22-F22)*G22 -> 414 | I22: 1.1 | J22: =H22*I22 -> 455.4 | K22: =(E22-F22)*G22*I22 -> 455.4 | N22: =K22 -> 455.4 | O22: 455
A23: 15 | B23: 代家鹏 | C23: 车间 | D23: 135358 | E23: 265.8 | F23: 247.9 | G23: 40 | H23: =(E23-F23)*G23 -> 716 | I23: 1.1 | J23: =H23*I23 -> 787.6 | K23: =(E23-F23)*G23*I23 -> 787.6 | N23: =K23 -> 787.6 | O23: 787.6
A24: 16 | B24: 代家静 | C24: 车间 | D24: 135380 | E24: 380.2 | F24: 354.3 | G24: 40 | H24: =(E24-F24)*G24 -> 1036 | I24: 1.1 | J24: =H24*I24 -> 1139.6 | K24: =(E24-F24)*G24*I24 -> 1139.6 | N24: =K24 -> 1139.6 | O24: 1139
A25: 17 | B25: 崔汝波 | C25: 车间 | D25: 135376 | E25: 43.8 | F25: 41.7 | G25: 40 | H25: =(E25-F25)*G25 -> 84 | I25: 1.1 | J25: =H25*I25 -> 92.4 | K25: =(E25-F25)*G25*I25 -> 92.4 | N25: =K25 -> 92.4 | O25: 93
A26: 18 | B26: 崔大洪 | C26: 车间 | D26: 无 | E26: 726 | F26: 676 | G26: 1 | H26: =(E26-F26)*G26 -> 50 | I26: 1.1 | J26: =H26*I26 -> 55 | K26: =(E26-F26)*G26*I26 -> 55 | N26: =K26 -> 55 | O26: 55
A27: 19 | B27: 崔大云 | C27: 车间 | D27: 无 | E27: 3389 | F27: 3040 | G27: 1 | H27: =(E27-F27)*G27 -> 349 | I27: 1.1 | J27: =H27*I27 -> 383.9 | K27: =(E27-F27)*G27*I27 -> 383.9 | N27: =K27 -> 383.9 | O27: 383.9
A28: 20 | B28: 冯成 | C28: 车间 | D28: 281917 | E28: 105.7 | F28: 92.1 | G28: 100 | H28: =(E28-F28)*G28 -> 1360 | I28: 1.1 | J28: =H28*I28 -> 1496 | K28: =(E28-F28)*G28*I28 -> 1496 | N28: =K28 -> 1496 | O28: 1496
A29: 21 | B29: 崔汝义 | C29: 车间 | D29: 136865 | E29: 373.9 | F29: 359 | G29: 20 | H29: =(E29-F29)*G29 -> 298 | I29: 1.1 | J29: =H29*I29 -> 327.8 | K29: =(E29-F29)*G29*I29 -> 327.8 | N29: =K29 -> 327.8 | O29: 327.8
A30: 22 | B30: 崔文交 | C30: 车间 | D30: 121780 | E30: 89.4 | F30: 82.9 | G30: 20 | H30: =(E30-F30)*G30 -> 130 | I30: 1.1 | J30: =H30*I30 -> 143 | K30: =(E30-F30)*G30*I30 -> 143 | N30: =K30 -> 143 | O30: 143
A31: 23 | B31: 马世平 | C31: 车间 | D31: 135940 | E31: 61.6 | F31: 55.7 | G31: 30 | H31: =(E31-F31)*G31 -> 177 | I31: 1.1 | J31: =H31*I31 -> 194.7 | K31: =(E31-F31)*G31*I31 -> 194.7 | N31: =K31 -> 194.7 | O31: 195
A32: 24 | B32: 崔文洪 | C32: 车间 | D32: 121780 | E32: 3973.2 | F32: 3733.7 | G32: 30 | H32: =(E32-F32)*G32 -> 7185 | I32: 1.1 | J32: =H32*I32 -> 7903.5 | K32: =(E32-F32)*G32*I32 -> 7903.5 | N32: 0
A33: 25 | B33: 昭通煜成再生资源有限公司 | C33: 车间 | D33: 134768 | E33: 1003 | F33: 970.5 | G33: 80 | H33: =(E33-F33)*G33 -> 2600 | I33: 1.1 | J33: =H33*I33 -> 2860 | K33: =(E33-F33)*G33*I33 -> 2860 | N33: =K33 -> 2860 | O33: 2860
A34: 27 | B34: 杨文仁 | C34: 车间 | D34: 135939 | E34: 216.8 | F34: 161.6 | G34: 80 | H34: =(E34-F34)*G34 -> 4416 | I34: 1.1 | J34: =H34*I34 -> 4857.6 | K34: =(E34-F34)*G34*I34 -> 4857.6 | N34: =K34 -> 4857.6 | O34: 4858
A35: 28 | B35: 创峰建材 | C35: 车间 | D35: 施工用电 | E35: 120.1 | F35: 86.8 | G35: 80 | H35: =(E35-F35)*G35 -> 2664 | I35: 1.1 | J35: =H35*I35 -> 2930.4 | K35: =(E35-F35)*G35*I35 -> 2930.4 | N35: =K35 -> 2930.4 | O35: 2930
A36: . | H36: =SUM(H3:H35) -> 45003 | J36: =SUM(J3:J35) -> 49503.3 | K36: =SUM(K3:K35) -> 49503.3 | N36: =SUM(N3:N35) -> 41599.8 | O36: =SUM(O3:O35) -> 41597.3
A37: 餐费： | C37: 1969+80打包盒（12月起收） | O37: =-1969-80 -> -2049
A38: 报销： | C38: 崔总转账发11月工资及朱良琦圆钢货款 | O38: 40000
C39: 11月工资 | O39: -37600
C40: 筛网用圆钢3300元*0.774吨+100元运费 | O40: =-3300*0.774-100 -> -2654.2
C41: 代缴11月电费 | O41: -30793.33
C42: 1月12日午餐及奶茶 | O42: =-270-78 -> -348
C43: 洒水车球阀 | O43: -50
C44: 1月17,19号清扫厂内卫生3个人*180*2 | O44: -1080
C45: 崔文洪购买柴油至崔宇文挖机 | O45: -1150
C46: 崔文洪购买柴油至崔宇文挖机 | O46: -520
A48: 余额： | O48: =O36+SUM(O37:O47)-591 -> 4761.77

Sheet 2026年1月水电费
A1: 宏发再生资源市场2026年1月电费收费清单
A2: 序号 | B2: 商户姓名 | C2: 分区 | D2: 电费 | L2: 水费 | Q2: 总计 | R2: 实收 | S2: 差额
D3: 电表编号 | E3: 本月抄表 | F3: 上月抄表 | G3: 倍率 | H3: 用电量 | I3: 单价 | J3: 小计 | K3: 合计 | L3: 上次抄表 | M3: 本次抄表 | N3: 用水量 | O3: 单价 | P3: 合计
A4: 1 | B4: 卯声平 | C4: 车间 | D4: 135407 | E4: 1606.4 | F4: 1507.4 | G4: 60 | H4: =(E4-F4)*G4 -> 5940 | I4: 1.1 | J4: =H4*I4 -> 6534 | K4: =J4+J5 -> 8165.3 | L4: 146 | M4: 146 | N4: =M4-L4 -> 0 | O4: 4.4 | P4: =O4*N4 -> 0 | Q4: =K4+P4+P5 -> 8794.5 | R4: 0 | S4: =Q4-R4 -> 8794.5
C5: 宿舍 | D5: 222933 | E5: 14816 | F5: 13333 | G5: 1 | H5: =(E5-F5)*G5 -> 1483 | I5: 1.1 | J5: =H5*I5 -> 1631.3 | L5: 182 | M5: 325 | N5: =M5-L5 -> 143 | O5: 4.4 | P5: =O5*N5 -> 629.2
A6: 2 | B6: 王银全 | C6: 车间 | D6: 135406 | E6: 684.5 | F6: 620.2 | G6: 40 | H6: =(E6-F6)*G6 -> 2572 | I6: 1.1 | J6: =H6*I6 -> 2829.2 | K6: =J6 -> 2829.2 | L6: 164 | M6: 239 | N6: =M6-L6 -> 75 | O6: 4.4 | P6: =O6*N6 -> 330 | Q6: =K6+P6 -> 3159.2 | R6: 0 | S6: =Q6-R6 -> 3159.2
A7: 3 | B7: 谢贤祥 | C7: 车间 | D7: 135400 | E7: 16.2 | F7: 15.5 | G7: 40 | H7: =(E7-F7)*G7 -> 28 | I7: 1.1 | J7: =H7*I7 -> 30.8 | K7: =J7+J8 -> 83.6 | L7: 55 | M7: 79 | N7: =M7-L7 -> 24 | O7: 4.4 | P7: =O7*N7 -> 105.6 | Q7: =K7+P7+P8 -> 299.2 | R7: 83.6 | S7: =Q7-R7 -> 215.6
C8: 宿舍 | D8: 无 | E8: 953 | F8: 905 | G8: 1 | H8: =(E8-F8)*G8 -> 48 | I8: 1.1 | J8: =H8*I8 -> 52.8 | L8: 13 | M8: 38 | N8: =M8-L8 -> 25 | O8: 4.4 | P8: =O8*N8 -> 110
A9: 4 | B9: 王银福 | C9: 车间 | D9: 135405 | E9: 544.4 | F9: 514 | G9: 40 | H9: =(E9-F9)*G9 -> 1216 | I9: 1.1 | J9: =H9*I9 -> 1337.6 | K9: =J9+J10 -> 1419 | L9: 155 | M9: 262 | N9: =M9-L9 -> 107 | O9: 4.4 | P9: =O9*N9 -> 470.8 | Q9: =K9+P9+P10 -> 1889.8 | R9: 0 | S9: =Q9-R9 -> 1889.8
C10: 宿舍 | D10: 无 | E10: 242 | F10: 168 | G10: 1 | H10: =(E10-F10)*G10 -> 74 | I10: 1.1 | J10: =H10*I10 -> 81.4 | N10: =M10-L10 -> 0 | O10: 4.4 | P10: =O10*N10 -> 0
A11: 5 | B11: 王文奇 | C11: 车间 | D11: 135401 | E11: 105.9 | F11: 99.5 | G11: 20 | H11: =(E11-F11)*G11 -> 128 | I11: 1.1 | J11: =H11*I11 -> 140.8 | K11: =J11 -> 140.8 | L11: 8 | M11: 11 | N11: =M11-L11 -> 3 | O11: 4.4 | P11: =O11*N11 -> 13.2 | Q11: =K11+P11 -> 154 | R11: 154 | S11: =Q11-R11 -> 0
A12: 6 | B12: 李兴平 | C12: 车间一 | D12: 135402 | E12: 919.8 | F12: 826.1 | G12: 20 | H12: =(E12-F12)*G12 -> 1874 | I12: 1.1 | J12: =H12*I12 -> 2061.4 | K12: =J12+J13+J14 -> 3086.6 | L12: 166 | M12: 283 | N12: =M12-L12 -> 117 | O12: 4.4 | P12: =O12*N12 -> 514.8 | Q12: =K12+P12+P13+P14 -> 3601.4 | R12: 3601 | S12: =Q12-R12 -> 0.4
C13: 车间二 | D13: 135408 | E13: 323.1 | F13: 319.8 | G13: 40 | H13: =(E13-F13)*G13 -> 132 | I13: 1.1 | J13: =H13*I13 -> 145.2 | N13: =M13-L13 -> 0 | O13: 4.4 | P13: =O13*N13 -> 0
C14: 车间三 | D14: 120279 | E14: 34.6 | F14: 14.6 | G14: 40 | H14: =(E14-F14)*G14 -> 800 | I14: 1.1 | J14: =H14*I14 -> 880 | N14: =M14-L14 -> 0 | O14: 4.4 | P14: =O14*N14 -> 0
A15: 7 | B15: 金耀 | C15: 车间 | D15: 136866 | E15: 284.1 | F15: 276.4 | G15: 20 | H15: =(E15-F15)*G15 -> 154 | I15: 1.1 | J15: =H15*I15 -> 169.4 | K15: =J15 -> 169.4 | L15: 20 | M15: 32 | N15: =M15-L15 -> 12 | O15: 4.4 | P15: =O15*N15 -> 52.8 | Q15: =K15+P15 -> 222.2 | R15: 222.2 | S15: =Q15-R15 -> 1.0231815e-12
A16: 8 | B16: 代家超 | C16: 车间 | D16: 135847 | E16: 273.9 | F16: 260.4 | G16: 40 | H16: =(E16-F16)*G16 -> 540 | I16: 1.1 | J16: =H16*I16 -> 594 | K16: =J16 -> 594 | L16: 61 | M16: 91 | N16: =M16-L16 -> 30 | O16: 4.4 | P16: =O16*N16 -> 132 | Q16: =K16+P16 -> 726 | R16: 726 | S16: =Q16-R16 -> 0
A17: 9 | B17: 崔宇文 | C17: 车间 | D17: 135848 | E17: 993.6 | F17: 913.3 | G17: 40 | H17: =(E17-F17)*G17 -> 3212 | I17: 1.1 | J17: =H17*I17 -> 3533.2 | K17: =J17 -> 3533.2 | L17: 18 | M17: 27 | N17: =M17-L17 -> 9 | O17: 4.4 | P17: =O17*N17 -> 39.6 | Q17: =K17+P17 -> 3572.8 | R17: 0 | S17: =Q17-R17 -> 3572.8
A18: 10 | B18: 崔玉文 | C18: 车间 | D18: 135846 | E18: 876.3 | F18: 824.8 | G18: 40 | H18: =(E18-F18)*G18 -> 2060 | I18: 1.1 | J18: =H18*I18 -> 2266 | K18: =J18+J19 -> 3137.2 | L18: 5 | M18: 10 | N18: =M18-L18 -> 5 | O18: 4.4 | P18: =O18*N18 -> 22 | Q18: =K18+P18+P19 -> 3159.2 | R18: 3159 | S18: =Q18-R18 -> 0.2
D19: 135379 | E19: 66.4 | F19: 56.5 | G19: 80 | H19: =(E19-F19)*G19 -> 792 | I19: 1.1 | J19: =H19*I19 -> 871.2 | N19: =M19-L19 -> 0 | O19: 4.4 | P19: =O19*N19 -> 0
A20: 11 | B20: 祖维成 | C20: 车间 | D20: 135845 | E20: 599.4 | F20: 554.6 | G20: 40 | H20: =(E20-F20)*G20 -> 1792 | I20: 1.1 | J20: =H20*I20 -> 1971.2 | K20: =J20 -> 1971.2 | L20: 155 | M20: 240 | N20: =M20-L20 -> 85 | O20: 4.4 | P20: =O20*N20 -> 374 | Q20: =K20+P20 -> 2345.2 | R20: 2345 | S20: =Q20-R20 -> 0.2
A21: 12 | B21: 崔大冲 | C21: 车间 | D21: 135844 | E21: 92.1 | F21: 83.5 | G21: 30 | H21: =(E21-F21)*G21 -> 258 | I21: 1.1 | J21: =H21*I21 -> 283.8 | K21: =J21 -> 283.8 | L21: 17 | M21: 33 | N21: =M21-L21 -> 16 | O21: 4.4 | P21: =O21*N21 -> 70.4 | Q21: =K21+P21 -> 354.2 | R21: 0 | S21: =Q21-R21 -> 354.2
A22: 13 | B22: 李世坤 | C22: 车间 | D22: 135844 | E22: 124 | F22: 107.8 | G22: 30 | H22: =(E22-F22)*G22 -> 486 | I22: 1.1 | J22: =H22*I22 -> 534.6 | K22: =J22 -> 534.6 | L22: 19 | M22: 61 | N22: =M22-L22 -> 42 | O22: 4.4 | P22: =O22*N22 -> 184.8 | Q22: =K22+P22 -> 719.4 | R22: 719.4 | S22: =Q22-R22 -> 0
A23: 14 | B23: 代家虎 | C23: 车间 | D23: 135850 | E23: 244.2 | F23: 237.7 | G23: 30 | H23: =(E23-F23)*G23 -> 195 | I23: 1.1 | J23: =H23*I23 -> 214.5 | K23: =J23 -> 214.5 | L23: 37 | M23: 46 | N23: =M23-L23 -> 9 | O23: 4.4 | P23: =O23*N23 -> 39.6 | Q23: =K23+P23 -> 254.1 | R23: 254 | S23: =Q23-R23 -> 0.1
A24: 15 | B24: 代家鹏 | C24: 车间 | D24: 135358 | E24: 290.1 | F24: 265.8 | G24: 40 | H24: =(E24-F24)*G24 -> 972 | I24: 1.1 | J24: =H24*I24 -> 1069.2 | K24: =J24 -> 1069.2 | L24: 105 | M24: 193 | N24: =M24-L24 -> 88 | O24: 4.4 | P24: =O24*N24 -> 387.2 | Q24: =K24+P24 -> 1456.4 | R24: 1456 | S24: =Q24-R24 -> 0.4
A25: 16 | B25: 代家静 | C25: 车间 | D25: 135380 | E25: 408.4 | F25: 380.2 | G25: 40 | H25: =(E25-F25)*G25 -> 1128 | I25: 1.1 | J25: =H25*I25 -> 1240.8 | K25: =J25 -> 1240.8 | L25: 110 | M25: 207 | N25: =M25-L25 -> 97 | O25: 4.4 | P25: =O25*N25 -> 426.8 | Q25: =K25+P25 -> 1667.6 | R25: 1667 | S25: =Q25-R25 -> 0.6
A26: 17 | B26: 崔汝波 | C26: 车间 | D26: 135376 | E26: 45.9 | F26: 43.8 | G26: 40 | H26: =(E26-F26)*G26 -> 84 | I26: 1.1 | J26: =H26*I26 -> 92.4 | K26: =J26 -> 92.4 | L26: 59 | M26: 80 | N26: =M26-L26 -> 21 | O26: 4.4 | P26: =O26*N26 -> 92.4 | Q26: =K26+P26 -> 184.8 | R26: 150 | S26: =Q26-R26 -> 34.8
A27: 18 | B27: 崔大洪 | C27: 车间 | D27: 无 | E27: 790 | F27: 726 | G27: 1 | H27: =(E27-F27)*G27 -> 64 | I27: 1.1 | J27: =H27*I27 -> 70.4 | K27: =J27 -> 70.4 | L27: 9 | M27: 17 | N27: =M27-L27 -> 8 | O27: 4.4 | P27: =O27*N27 -> 35.2 | Q27: =K27+P27 -> 105.6 | R27: 105.6 | S27: =Q27-R27 -> 0
A28: 19 | B28: 崔大云 | C28: 车间 | D28: 无 | E28: 3691 | F28: 3389 | G28: 1 | H28: =(E28-F28)*G28 -> 302 | I28: 1.1 | J28: =H28*I28 -> 332.2 | K28: =J28 -> 332.2 | L28: 38 | M28: 83 | N28: =M28-L28 -> 45 | O28: 4.4 | P28: =O28*N28 -> 198 | Q28: =K28+P28 -> 530.2 | R28: 530.2 | S28: =Q28-R28 -> 0
A29: 20 | B29: 冯成 | C29: 车间 | D29: 281917 | E29: 133.5 | F29: 105.7 | G29: 100 | H29: =(E29-F29)*G29 -> 2780 | I29: 1.1 | J29: =H29*I29 -> 3058 | K29: =J29 -> 3058 | L29: 9 | M29: 14 | N29: =M29-L29 -> 5 | O29: 4.4 | P29: =O29*N29 -> 22 | Q29: =K29+P29 -> 3080 | R29: 3080 | S29: =Q29-R29 -> 0
A30: 21 | B30: 崔汝义 | C30: 车间 | D30: 136865 | E30: 391.7 | F30: 373.9 | G30: 20 | H30: =(E30-F30)*G30 -> 356 | I30: 1.1 | J30: =H30*I30 -> 391.6 | K30: =J30 -> 391.6 | L30: 4 | M30: 7 | N30: =M30-L30 -> 3 | O30: 4.4 | P30: =O30*N30 -> 13.2 | Q30: =K30+P30 -> 404.8 | R30: 404.8 | S30: =Q30-R30 -> 0
A31: 22 | B31: 崔文交 | C31: 车间 | D31: 121780 | E31: 97.5 | F31: 89.4 | G31: 20 | H31: =(E31-F31)*G31 -> 162 | I31: 1.1 | J31: =H31*I31 -> 178.2 | K31: =J31 -> 178.2 | L31: 38 | M31: 89 | N31: =M31-L31 -> 51 | O31: 4.4 | P31: =O31*N31 -> 224.4 | Q31: =K31+P31 -> 402.6 | R31: 403 | S31: =Q31-R31 -> -0.4
A32: 23 | B32: 马世平 | C32: 车间 | D32: 135940 | E32: 67.8 | F32: 61.6 | G32: 30 | H32: =(E32-F32)*G32 -> 186 | I32: 1.1 | J32: =H32*I32 -> 204.6 | K32: =J32 -> 204.6 | L32: 3 | M32: 7 | N32: =M32-L32 -> 4 | O32: 4.4 | P32: =O32*N32 -> 17.6 | Q32: =K32+P32 -> 222.2 | R32: 223 | S32: =Q32-R32 -> -0.8
A33: 24 | B33: 崔文洪 | C33: 生活 | D33: 无 | E33: 0 | F33: 0 | G33: 0 | H33: 0 | I33: 0 | J33: 0 | L33: 258 | M33: 556 | N33: =M33-L33 -> 298 | O33: 4.4 | P33: =O33*N33 -> 1311.2 | Q33: 1548.8 | R33: 1550 | S33: =Q33-R33 -> -1.2
C34: 车间 | D34: 121780 | E34: 4211.7 | F34: 3973.2 | G34: 30 | H34: =(E34-F34)*G34 -> 7155 | I34: 1.1 | J34: =H34*I34 -> 7870.5 | L34: 73 | M34: 127 | N34: =M34-L34 -> 54 | O34: 4.4 | P34: =O34*N34 -> 237.6
A35: 25 | B35: 昭通煜成再生资源有限公司 | C35: 宿舍 | D35: 无 | E35: 203 | F35: 24 | G35: 1 | H35: =(E35-F35)*G35 -> 179 | I35: 1.1 | J35: =H35*I35 -> 196.9 | K35: =J35+J36 -> 9084.9 | L35: 23 | M35: 73 | N35: =M35-L35 -> 50 | O35: 4.4 | P35: =O35*N35 -> 220 | Q35: =K35+P35+P36 -> 9304.9 | R35: 0 | S35: =Q35-R35 -> 9304.9
C36: 车间 | D36: 134768 | E36: 1104 | F36: 1003 | G36: 80 | H36: =(E36-F36)*G36 -> 8080 | I36: 1.1 | J36: =H36*I36 -> 8888 | N36: =M36-L36 -> 0 | O36: 4.4 | P36: =O36*N36 -> 0
A37: 27 | B37: 杨文仁 | C37: 车间 | D37: 135939 | E37: 261.8 | F37: 216.8 | G37: 80 | H37: =(E37-F37)*G37 -> 3600 | I37: 1.1 | J37: =H37*I37 -> 3960 | K37: =J37 -> 3960 | L37: 0 | M37: 2 | N37: =M37-L37 -> 2 | O37: 4.4 | P37: =O37*N37 -> 8.8 | Q37: =K37+P37 -> 3968.8 | R37: 0 | S37: =Q37-R37 -> 3968.8
A38: 28 | B38: 创峰建材 | C38: 车间 | D38: 施工用电 | E38: 141 | F38: 120.1 | G38: 80 | H38: =(E38-F38)*G38 -> 1672 | I38: 1.1 | J38: =H38*I38 -> 1839.2 | K38: =J38 -> 1839.2 | L38: 0 | M38: 8 | N38: =M38-L38 -> 8 | O38: 4.4 | P38: =O38*N38 -> 35.2 | Q38: =K38+P38 -> 1874.4 | R38: 1839 | S38: =Q38-R38 -> 35.4
H39: =SUM(H4:H38) -> 50504 | J39: =SUM(J4:J38) -> 55554.4 | K39: =SUM(K4:K38) -> 47683.9 | N39: =SUM(N4:N38) -> 1436 | Q39: =SUM(Q4:Q38) -> 54002.3 | R39: =SUM(R4:R38) -> 22672.8 | S39: =SUM(S4:S38) -> 31329.5
A40: 餐费： | C40: 1855+80打包盒（12月起收） | R40: =-1855-80 -> -1935
A41: 报销： | C41: 杨华垃圾车停放误工费 | R41: -6000
C42: 华新垃圾往返路费 | R42: -700
C43: 厂区清扫杂工费1月25、2月1日，2月8日（3*180*3+180*1[配合蒋安坤拉电]） | R43: -1800
C44: 厂区清扫杂工费1月17,19日 | R44: -1080
C45: 王银福新场地电力搭建电缆及电气配件 | R45: -3813
C46: 崔宇文轨道钢286kg+257kg | R46: =-2600*(0.237+0.286) -> -1359.8
C47: 崔玉文工字钢1420kg | R47: =-1.42*2000 -> -2840
C48: 李世坤工字钢579kg
C49: 2025年12月电费 | R49: -32807.46
C50: 上月电费结转 | R50: ='2025年12月电费'!O48 -> 4761.77
C51: 宽带充值 | R51: -1000
A52: 小计： | R52: =SUM(R40:R51) -> -48573.49
A53: 余额： | R53: =R39+R52 -> -25900.69

Sheet 2026年2月水电费
A1: 宏发再生资源市场2026年2月电费收费清单
A2: 序号 | B2: 商户姓名 | C2: 分区 | D2: 电费 | L2: 水费 | Q2: 上月欠缴 | R2: 总计 | S2: 实收
D3: 电表编号 | E3: 本月抄表 | F3: 上月抄表 | G3: 倍率 | H3: 用电量 | I3: 单价 | J3: 小计 | K3: 合计 | L3: 上次抄表 | M3: 本次抄表 | N3: 用水量 | O3: 单价 | P3: 合计
A4: 1 | B4: 卯声平 | C4: 车间 | D4: 135407 | E4: 1622.2 | F4: 1606.4 | G4: 60 | H4: =(E4-F4)*G4 -> 948 | I4: 1.1 | J4: =H4*I4 -> 1042.8 | K4: =J4+J5 -> 1438.8 | L4: 146 | M4: 146 | N4: =M4-L4 -> 0 | O4: 4.4 | P4: =O4*N4 -> 0 | Q4: 8794.5 | R4: =K4+P4+P5+Q4 -> 10233.3 | S4: 10233
C5: 宿舍 | D5: 222933 | E5: 15176 | F5: 14816 | G5: 1 | H5: =(E5-F5)*G5 -> 360 | I5: 1.1 | J5: =H5*I5 -> 396 | L5: 325 | M5: 325 | N5: =M5-L5 -> 0 | O5: 4.4 | P5: =O5*N5 -> 0
A6: 2 | B6: 王银全 | C6: 车间 | D6: 135406 | E6: 704.4 | F6: 684.5 | G6: 40 | H6: =(E6-F6)*G6 -> 796 | I6: 1.1 | J6: =H6*I6 -> 875.6 | K6: =J6 -> 875.6 | L6: 239 | M6: 239 | N6: =M6-L6 -> 0 | O6: 4.4 | P6: =O6*N6 -> 0 | Q6: 3159.2 | R6: =K6+P6+Q6 -> 4034.8 | S6: 4034
A7: 3 | B7: 谢贤祥 | C7: 车间 | D7: 135400 | E7: 16.6 | F7: 16.2 | G7: 40 | H7: =(E7-F7)*G7 -> 16 | I7: 1.1 | J7: =H7*I7 -> 17.6 | K7: =J7+J8 -> 47.3 | L7: 79 | M7: 79 | N7: =M7-L7 -> 0 | O7: 4.4 | P7: =O7*N7 -> 0 | Q7: 215.6 | R7: =K7+P7+P8+Q7 -> 262.9 | S7: 262.9
C8: 宿舍 | D8: 无 | E8: 980 | F8: 953 | G8: 1 | H8: =(E8-F8)*G8 -> 27 | I8: 1.1 | J8: =H8*I8 -> 29.7 | L8: 38 | M8: 38 | N8: =M8-L8 -> 0 | O8: 4.4 | P8: =O8*N8 -> 0
A9: 4 | B9: 王银福 | C9: 车间 | D9: 135405 | E9: 552.5 | F9: 544.4 | G9: 40 | H9: =(E9-F9)*G9 -> 324 | I9: 1.1 | J9: =H9*I9 -> 356.4 | K9: =J9+J10+J11+J12+J13 -> 1035.1 | L9: 262 | M9: 262 | N9: =M9-L9 -> 0 | O9: 4.4 | P9: =O9*N9 -> 0 | Q9: 1889.8 | R9: =K9+P9+P10+Q9 -> 2924.9 | S9: 2925
C10: 宿舍 | D10: 无 | E10: 256 | F10: 242 | G10: 1 | H10: =(E10-F10)*G10 -> 14 | I10: 1.1 | J10: =H10*I10 -> 15.4 | N10: =M10-L10 -> 0 | O10: 4.4 | P10: =O10*N10 -> 0
C11: 施工 | D11: 无 | E11: 1535 | F11: 1109 | G11: 1 | H11: =(E11-F11)*G11 -> 426 | I11: 1.1 | J11: =H11*I11 -> 468.6
C12: 食堂1 | D12: 无 | E12: 4199 | F12: 4023 | G12: 1 | H12: =(E12-F12)*G12 -> 176 | I12: 1.1 | J12: =H12*I12 -> 193.6
C13: 食堂2 | D13: 无 | E13: 6111 | F13: 6110 | G13: 1 | H13: =(E13-F13)*G13 -> 1 | I13: 1.1 | J13: =H13*I13 -> 1.1
A14: 5 | B14: 王文奇 | C14: 车间 | D14: 135401 | E14: 109.9 | F14: 105.9 | G14: 20 | H14: =(E14-F14)*G14 -> 80 | I14: 1.1 | J14: =H14*I14 -> 88 | K14: =J14 -> 88 | L14: 11 | M14: 11 | N14: =M14-L14 -> 0 | O14: 4.4 | P14: =O14*N14 -> 0 | Q14: 0 | R14: =K14+P14 -> 88 | S14: 88
A15: 6 | B15: 李兴平 | C15: 车间一 | D15: 135402 | E15: 953.7 | F15: 919.8 | G15: 20 | H15: =(E15-F15)*G15 -> 678 | I15: 1.1 | J15: =H15*I15 -> 745.8 | K15: =J15+J16+J17 -> 1128.6 | L15: 283 | M15: 283 | N15: =M15-L15 -> 0 | O15: 4.4 | P15: =O15*N15 -> 0 | Q15: 0 | R15: =K15+P15+P16+P17 -> 1128.6 | S15: 1128
C16: 车间二 | D16: 135408 | E16: 323.1 | F16: 323.1 | G16: 40 | H16: =(E16-F16)*G16 -> 0 | I16: 1.1 | J16: =H16*I16 -> 0 | N16: =M16-L16 -> 0 | O16: 4.4 | P16: =O16*N16 -> 0
C17: 车间三 | D17: 120279 | E17: 43.3 | F17: 34.6 | G17: 40 | H17: =(E17-F17)*G17 -> 348 | I17: 1.1 | J17: =H17*I17 -> 382.8 | N17: =M17-L17 -> 0 | O17: 4.4 | P17: =O17*N17 -> 0
A18: 7 | B18: 金耀 | C18: 车间 | D18: 136866 | E18: 288.4 | F18: 284.1 | G18: 20 | H18: =(E18-F18)*G18 -> 86 | I18: 1.1 | J18: =H18*I18 -> 94.6 | K18: =J18 -> 94.6 | L18: 32 | M18: 32 | N18: =M18-L18 -> 0 | O18: 4.4 | P18: =O18*N18 -> 0 | Q18: 0 | R18: =K18+P18 -> 94.6 | S18: 94.6
A19: 8 | B19: 代家超 | C19: 车间 | D19: 135847 | E19: 284.7 | F19: 273.9 | G19: 40 | H19: =(E19-F19)*G19 -> 432 | I19: 1.1 | J19: =H19*I19 -> 475.2 | K19: =J19 -> 475.2 | L19: 91 | M19: 91 | N19: =M19-L19 -> 0 | O19: 4.4 | P19: =O19*N19 -> 0 | Q19: 0 | R19: =K19+P19 -> 475.2 | S19: 475
A20: 9 | B20: 崔宇文 | C20: 车间 | D20: 135848 | E20: 1028.7 | F20: 993.6 | G20: 40 | H20: =(E20-F20)*G20 -> 1404 | I20: 1.1 | J20: =H20*I20 -> 1544.4 | K20: =J20 -> 1544.4 | L20: 27 | M20: 27 | N20: =M20-L20 -> 0 | O20: 4.4 | P20: =O20*N20 -> 0 | Q20: 3572.8 | R20: =K20+P20+Q20 -> 5117.2 | S20: 5117.2
A21: 10 | B21: 崔玉文 | C21: 车间 | D21: 135846 | E21: 894.6 | F21: 876.3 | G21: 40 | H21: =(E21-F21)*G21 -> 732 | I21: 1.1 | J21: =H21*I21 -> 805.2 | K21: =J21+J22 -> 1271.6 | L21: 10 | M21: 10 | N21: =M21-L21 -> 0 | O21: 4.4 | P21: =O21*N21 -> 0 | Q21: 0 | R21: =K21+P21+P22 -> 1271.6 | S21: 1271
D22: 135379 | E22: 71.7 | F22: 66.4 | G22: 80 | H22: =(E22-F22)*G22 -> 424 | I22: 1.1 | J22: =H22*I22 -> 466.4 | N22: =M22-L22 -> 0 | O22: 4.4 | P22: =O22*N22 -> 0
A23: 11 | B23: 祖维成 | C23: 车间 | D23: 135845 | E23: 621.8 | F23: 599.4 | G23: 40 | H23: =(E23-F23)*G23 -> 896 | I23: 1.1 | J23: =H23*I23 -> 985.6 | K23: =J23 -> 985.6 | L23: 240 | M23: 240 | N23: =M23-L23 -> 0 | O23: 4.4 | P23: =O23*N23 -> 0 | Q23: 0 | R23: =K23+P23 -> 985.6 | S23: 985
A24: 12 | B24: 崔大冲 | C24: 车间 | D24: 135844 | E24: 97.4 | F24: 92.1 | G24: 30 | H24: =(E24-F24)*G24 -> 159 | I24: 1.1 | J24: =H24*I24 -> 174.9 | K24: =J24 -> 174.9 | L24: 33 | M24: 33 | N24: =M24-L24 -> 0 | O24: 4.4 | P24: =O24*N24 -> 0 | Q24: 354.2 | R24: =K24+P24+Q24 -> 529.1 | S24: 529
A25: 13 | B25: 李世坤 | C25: 车间 | D25: 135844 | E25: 139.7 | F25: 124 | G25: 30 | H25: =(E25-F25)*G25 -> 471 | I25: 1.1 | J25: =H25*I25 -> 518.1 | K25: =J25 -> 518.1 | L25: 61 | M25: 61 | N25: =M25-L25 -> 0 | O25: 4.4 | P25: =O25*N25 -> 0 | Q25: 0 | R25: =K25+P25 -> 518.1 | S25: 518
A26: 14 | B26: 代家虎 | C26: 车间 | D26: 135850 | E26: 248.8 | F26: 244.2 | G26: 30 | H26: =(E26-F26)*G26 -> 138 | I26: 1.1 | J26: =H26*I26 -> 151.8 | K26: =J26 -> 151.8 | L26: 46 | M26: 46 | N26: =M26-L26 -> 0 | O26: 4.4 | P26: =O26*N26 -> 0 | Q26: 0 | R26: =K26+P26 -> 151.8 | S26: 151
A27: 15 | B27: 代家鹏 | C27: 车间 | D27: 135358 | E27: 310.8 | F27: 290.1 | G27: 40 | H27: =(E27-F27)*G27 -> 828 | I27: 1.1 | J27: =H27*I27 -> 910.8 | K27: =J27 -> 910.8 | L27: 193 | M27: 193 | N27: =M27-L27 -> 0 | O27: 4.4 | P27: =O27*N27 -> 0 | Q27: 0 | R27: =K27+P27 -> 910.8 | S27: 910
A28: 16 | B28: 代家静 | C28: 车间 | D28: 135380 | E28: 436.9 | F28: 408.4 | G28: 40 | H28: =(E28-F28)*G28 -> 1140 | I28: 1.1 | J28: =H28*I28 -> 1254 | K28: =J28 -> 1254 | L28: 207 | M28: 207 | N28: =M28-L28 -> 0 | O28: 4.4 | P28: =O28*N28 -> 0 | Q28: 0 | R28: =K28+P28 -> 1254 | S28: 1254
A29: 17 | B29: 崔汝波 | C29: 车间 | D29: 135376 | E29: 47.5 | F29: 45.9 | G29: 40 | H29: =(E29-F29)*G29 -> 64 | I29: 1.1 | J29: =H29*I29 -> 70.4 | K29: =J29 -> 70.4 | L29: 80 | M29: 80 | N29: =M29-L29 -> 0 | O29: 4.4 | P29: =O29*N29 -> 0 | Q29: 34.2 | R29: =K29+P29+Q29 -> 104.6 | S29: 105
A30: 18 | B30: 崔大洪 | C30: 车间 | D30: 无 | E30: 820 | F30: 790 | G30: 1 | H30: =(E30-F30)*G30 -> 30 | I30: 1.1 | J30: =H30*I30 -> 33 | K30: =J30 -> 33 | L30: 17 | M30: 17 | N30: =M30-L30 -> 0 | O30: 4.4 | P30: =O30*N30 -> 0 | Q30: 0 | R30: =K30+P30 -> 33
A31: 19 | B31: 崔大云 | C31: 车间 | D31: 无 | E31: 3848 | F31: 3691 | G31: 1 | H31: =(E31-F31)*G31 -> 157 | I31: 1.1 | J31: =H31*I31 -> 172.7 | K31: =J31 -> 172.7 | L31: 83 | M31: 83 | N31: =M31-L31 -> 0 | O31: 4.4 | P31: =O31*N31 -> 0 | Q31: 0 | R31: =K31+P31 -> 172.7 | S31: =172.7*2 -> 345.4
A32: 20 | B32: 冯成 | C32: 车间 | D32: 281917 | E32: 134.9 | F32: 133.5 | G32: 100 | H32: =(E32-F32)*G32 -> 140 | I32: 1.1 | J32: =H32*I32 -> 154 | K32: =J32 -> 154 | L32: 14 | M32: 14 | N32: =M32-L32 -> 0 | O32: 4.4 | P32: =O32*N32 -> 0 | Q32: 0 | R32: =K32+P32 -> 154 | S32: 154
A33: 21 | B33: 崔汝义 | C33: 车间 | D33: 136865 | E33: 405.5 | F33: 391.7 | G33: 20 | H33: =(E33-F33)*G33 -> 276 | I33: 1.1 | J33: =H33*I33 -> 303.6 | K33: =J33 -> 303.6 | L33: 7 | M33: 7 | N33: =M33-L33 -> 0 | O33: 4.4 | P33: =O33*N33 -> 0 | Q33: 0 | R33: =K33+P33 -> 303.6 | S33: 303.6
A34: 22 | B34: 崔文交 | C34: 车间 | D34: 121780 | E34: 103.9 | F34: 97.5 | G34: 20 | H34: =(E34-F34)*G34 -> 128 | I34: 1.1 | J34: =H34*I34 -> 140.8 | K34: =J34 -> 140.8 | L34: 89 | M34: 89 | N34: =M34-L34 -> 0 | O34: 4.4 | P34: =O34*N34 -> 0 | Q34: 0 | R34: =K34+P34 -> 140.8 | S34: 141
A35: 23 | B35: 马世平 | C35: 车间 | D35: 135940 | E35: 70.4 | F35: 67.8 | G35: 30 | H35: =(E35-F35)*G35 -> 78 | I35: 1.1 | J35: =H35*I35 -> 85.8 | K35: =J35 -> 85.8 | L35: 7 | M35: 7 | N35: =M35-L35 -> 0 | O35: 4.4 | P35: =O35*N35 -> 0 | Q35: 0 | R35: =K35+P35 -> 85.8 | S35: 86
A36: 24 | B36: 崔文洪 | C36: 生活 | D36: 无 | E36: 0 | F36: 0 | G36: 0 | H36: 0 | I36: 0 | J36: 0 | K36: 0 | L36: 556 | M36: 556 | N36: =M36-L36 -> 0 | O36: 4.4 | P36: =O36*N36 -> 0 | Q36: 0 | R36: 0
C37: 车间 | D37: 121780 | E37: 4415.1 | F37: 4211.7 | G37: 30 | H37: =(E37-F37)*G37 -> 6102 | I37: 1.1 | J37: =H37*I37 -> 6712.2 | K37: =J37 -> 6712.2 | L37: 127 | M37: 127 | N37: =M37-L37 -> 0 | O37: 4.4 | P37: =O37*N37 -> 0
A38: 25 | B38: 昭通煜成再生资源有限公司 | C38: 宿舍 | D38: 无 | E38: 204 | F38: 203 | G38: 1 | H38: =(E38-F38)*G38 -> 1 | I38: 1.1 | J38: =H38*I38 -> 1.1 | K38: =J38+J39 -> 986.7 | L38: 73 | M38: 73 | N38: =M38-L38 -> 0 | O38: 4.4 | P38: =O38*N38 -> 0 | Q38: 9304 | R38: =K38+P38+P39+Q38 -> 10290.7 | S38: 10290
C39: 车间 | D39: 134768 | E39: 1115.2 | F39: 1104 | G39: 80 | H39: =(E39-F39)*G39 -> 896 | I39: 1.1 | J39: =H39*I39 -> 985.6 | N39: =M39-L39 -> 0 | O39: 4.4 | P39: =O39*N39 -> 0
A40: 26 | B40: 杨文仁 | C40: 车间 | D40: 135939 | E40: 271.4 | F40: 261.8 | G40: 80 | H40: =(E40-F40)*G40 -> 768 | I40: 1.1 | J40: =H40*I40 -> 844.8 | K40: =J40+J41 -> 15848.8 | L40: 2 | M40: 2 | N40: =M40-L40 -> 0 | O40: 4.4 | P40: =O40*N40 -> 0 | Q40: 3968.8 | R40: =K40+P40+P41+Q40 -> 19817.6 | S40: 19817.6 | T40: =R40-S40 -> 0
C41: 车间 | D41: 121779 | E41: 136.4 | F41: 0 | G41: 100 | H41: =(E41-F41)*G41 -> 13640 | I41: 1.1 | J41: =H41*I41 -> 15004
A42: 27 | B42: 创峰建材 | C42: 车间 | D42: 施工用电 | E42: 152.2 | F42: 141 | G42: 80 | H42: =(E42-F42)*G42 -> 896 | I42: 1.1 | J42: =H42*I42 -> 985.6 | K42: =J42 -> 985.6 | L42: 8 | M42: 8 | N42: =M42-L42 -> 0 | O42: 4.4 | P42: =O42*N42 -> 0 | Q42: 35.4 | R42: =K42+P42+Q42 -> 1021 | S42: 1020
H43: =SUM(H4:H42) -> 34080 | J43: =SUM(J4:J42) -> 37488 | K43: =SUM(K4:K42) -> 37488 | N43: =SUM(N4:N42) -> 0 | Q43: =SUM(Q4:Q42) -> 31328.5 | R43: =SUM(R4:R42) -> 62104.3 | S43: =SUM(S4:S42) -> 62238.3 | T43: =R43-S43 -> -134
A44: 餐费： | C44: 1355餐费+80饭盒 | S44: =-1355-80 -> -1435
A45: 报销： | C45: 过磅小票热敏打印纸 | S45: -137.49
C46: 2026年1月电费 | S46: =-44951.88*1.001 -> -44996.832
C47: 2026-3-16 午餐晚餐 | S47: -60
C48: 上月电费结转 | S48: ='2026年1月水电费'!R53 -> -25900.69
C49: 崔总报账 | S49: 10248
A56: 小计： | S56: =SUM(S44:S55) -> -62282.012
A57: 余额： | S57: =S43+S56 -> -43.71188

Sheet 2026年3月水电费
A1: 宏发再生资源市场2026年3月电费收费清单
A2: 序号 | B2: 商户姓名 | C2: 分区 | D2: 电费 | L2: 水费 | Q2: 实收
D3: 电表编号 | E3: 本月抄表 | F3: 上月抄表 | G3: 倍率 | H3: 用电量 | I3: 单价 | J3: 小计 | K3: 合计 | L3: 上次抄表 | M3: 本次抄表 | N3: 用水量 | O3: 单价 | P3: 合计
A4: 1 | B4: 卯声平 | C4: 车间 | D4: 135407 | E4: 1683.4 | F4: 1622.2 | G4: 60 | H4: =(E4-F4)*G4 -> 3672 | I4: 1.1 | J4: =H4*I4 -> 4039.2 | K4: =J4+J5 -> 5253.6 | L4: 146 | M4: 146 | N4: =M4-L4 -> 0 | O4: 4.4 | P4: =O4*N4 -> 0 | Q4: 5253
C5: 宿舍 | D5: 222933 | E5: 16280 | F5: 15176 | G5: 1 | H5: =(E5-F5)*G5 -> 1104 | I5: 1.1 | J5: =H5*I5 -> 1214.4 | L5: 325 | M5: 325 | N5: =M5-L5 -> 0 | O5: 4.4 | P5: =O5*N5 -> 0
A6: 2 | B6: 王银全 | C6: 车间 | D6: 135406 | E6: 747.4 | F6: 704.4 | G6: 40 | H6: =(E6-F6)*G6 -> 1720 | I6: 1.1 | J6: =H6*I6 -> 1892 | K6: =J6+J7 -> 1922.8 | L6: 239 | M6: 239 | N6: =M6-L6 -> 0 | O6: 4.4 | P6: =O6*N6 -> 0 | Q6: 1922
C7: 宿舍 | D7: 无 | E7: 284 | F7: 256 | G7: 1 | H7: =(E7-F7)*G7 -> 28 | I7: 1.1 | J7: =H7*I7 -> 30.8
A8: 3 | B8: 谢贤祥 | C8: 车间 | D8: 135400 | E8: 17 | F8: 16.6 | G8: 40 | H8: =(E8-F8)*G8 -> 16 | I8: 1.1 | J8: =H8*I8 -> 17.6 | K8: =J8+J9+J10 -> 262.9 | L8: 79 | M8: 79 | N8: =M8-L8 -> 0 | O8: 4.4 | P8: =O8*N8 -> 0 | Q8: 262.9
C9: 宿舍 | D9: 无 | E9: 1017 | F9: 980 | G9: 1 | H9: =(E9-F9)*G9 -> 37 | I9: 1.1 | J9: =H9*I9 -> 40.7 | L9: 38 | M9: 38 | N9: =M9-L9 -> 0 | O9: 4.4 | P9: =O9*N9 -> 0
C10: 宿舍 | D10: 无 | E10: 186 | F10: 0 | G10: 1 | H10: =(E10-F10)*G10 -> 186 | I10: 1.1 | J10: =H10*I10 -> 204.6
A11: 4 | B11: 王银福 | C11: 车间 | D11: 135405 | E11: 553.9 | F11: 552.5 | G11: 40 | H11: =(E11-F11)*G11 -> 56 | I11: 1.1 | J11: =H11*I11 -> 61.6 | K11: =J11+J12+J13 -> 958.1 | L11: 262 | M11: 262 | N11: =M11-L11 -> 0 | O11: 4.4 | P11: =O11*N11 -> 0 | Q11: 958.1
C12: 新车间 | D12: 134770 | E12: 18.2 | F12: 0 | G12: 40 | H12: =(E12-F12)*G12 -> 728 | I12: 1.1 | J12: =H12*I12 -> 800.8
C13: 食堂2 | D13: 1 | E13: 4286 | F13: 4199 | G13: 1 | H13: =(E13-F13)*G13 -> 87 | I13: 1.1 | J13: =H13*I13 -> 95.7
A14: 5 | B14: 王文奇 | C14: 车间 | D14: 135401 | E14: 116.8 | F14: 109.9 | G14: 20 | H14: =(E14-F14)*G14 -> 138 | I14: 1.1 | J14: =H14*I14 -> 151.8 | K14: =J14 -> 151.8 | L14: 11 | M14: 11 | N14: =M14-L14 -> 0 | O14: 4.4 | P14: =O14*N14 -> 0 | Q14: 152
A15: 6 | B15: 李兴平 | C15: 车间一 | D15: 135402 | E15: 1029.9 | F15: 953.7 | G15: 20 | H15: =(E15-F15)*G15 -> 1524 | I15: 1.1 | J15: =H15*I15 -> 1676.4 | K15: =J15+J16 -> 2538.8 | L15: 283 | M15: 283 | N15: =M15-L15 -> 0 | O15: 4.4 | P15: =O15*N15 -> 0 | Q15: 2538
C16: 车间三 | D16: 120279 | E16: 62.9 | F16: 43.3 | G16: 40 | H16: =(E16-F16)*G16 -> 784 | I16: 1.1 | J16: =H16*I16 -> 862.4 | N16: =M16-L16 -> 0 | O16: 4.4 | P16: =O16*N16 -> 0
A17: 7 | B17: 金耀 | C17: 车间 | D17: 136866 | E17: 296.2 | F17: 288.4 | G17: 20 | H17: =(E17-F17)*G17 -> 156 | I17: 1.1 | J17: =H17*I17 -> 171.6 | K17: =J17 -> 171.6 | L17: 32 | M17: 32 | N17: =M17-L17 -> 0 | O17: 4.4 | P17: =O17*N17 -> 0 | Q17: 171.6
A18: 8 | B18: 代家超 | C18: 车间 | D18: 135847 | E18: 299.5 | F18: 284.7 | G18: 40 | H18: =(E18-F18)*G18 -> 592 | I18: 1.1 | J18: =H18*I18 -> 651.2 | K18: =J18 -> 651.2 | L18: 91 | M18: 91 | N18: =M18-L18 -> 0 | O18: 4.4 | P18: =O18*N18 -> 0 | Q18: 651
A19: 9 | B19: 崔宇文 | C19: 车间 | D19: 135848 | E19: 1096.9 | F19: 1028.7 | G19: 40 | H19: =(E19-F19)*G19 -> 2728 | I19: 1.1 | J19: =H19*I19 -> 3000.8 | K19: =J19 -> 3000.8 | L19: 27 | M19: 27 | N19: =M19-L19 -> 0 | O19: 4.4 | P19: =O19*N19 -> 0 | Q19: 3000
A20: 10 | B20: 崔玉文 | C20: 车间 | D20: 135846 | E20: 937.8 | F20: 894.6 | G20: 40 | H20: =(E20-F20)*G20 -> 1728 | I20: 1.1 | J20: =H20*I20 -> 1900.8 | K20: =J20+J21 -> 3352.8 | L20: 10 | M20: 10 | N20: =M20-L20 -> 0 | O20: 4.4 | P20: =O20*N20 -> 0 | Q20: 3352
D21: 135379 | E21: 88.2 | F21: 71.7 | G21: 80 | H21: =(E21-F21)*G21 -> 1320 | I21: 1.1 | J21: =H21*I21 -> 1452 | N21: =M21-L21 -> 0 | O21: 4.4 | P21: =O21*N21 -> 0
A22: 11 | B22: 祖维成 | C22: 车间 | D22: 135845 | E22: 663.7 | F22: 621.8 | G22: 40 | H22: =(E22-F22)*G22 -> 1676 | I22: 1.1 | J22: =H22*I22 -> 1843.6 | K22: =J22 -> 1843.6 | L22: 240 | M22: 240 | N22: =M22-L22 -> 0 | O22: 4.4 | P22: =O22*N22 -> 0 | Q22: 1843
A23: 12 | B23: 崔大冲 | C23: 车间 | D23: 135844 | E23: 102.3 | F23: 97.4 | G23: 30 | H23: =(E23-F23)*G23 -> 147 | I23: 1.1 | J23: =H23*I23 -> 161.7 | K23: =J23 -> 161.7 | L23: 33 | M23: 33 | N23: =M23-L23 -> 0 | O23: 4.4 | P23: =O23*N23 -> 0 | Q23: 161.7
A24: 13 | B24: 李世坤 | C24: 车间 | D24: 135851 | E24: 148.4 | F24: 139.7 | G24: 30 | H24: =(E24-F24)*G24 -> 261 | I24: 1.1 | J24: =H24*I24 -> 287.1 | K24: =J24 -> 287.1 | L24: 61 | M24: 61 | N24: =M24-L24 -> 0 | O24: 4.4 | P24: =O24*N24 -> 0 | Q24: 287
A25: 14 | B25: 代家虎 | C25: 车间 | D25: 135850 | E25: 259.1 | F25: 248.8 | G25: 30 | H25: =(E25-F25)*G25 -> 309 | I25: 1.1 | J25: =H25*I25 -> 339.9 | K25: =J25 -> 339.9 | L25: 46 | M25: 46 | N25: =M25-L25 -> 0 | O25: 4.4 | P25: =O25*N25 -> 0 | Q25: 339.9
A26: 15 | B26: 代家鹏 | C26: 车间 | D26: 135358 | E26: 326.5 | F26: 310.8 | G26: 40 | H26: =(E26-F26)*G26 -> 628 | I26: 1.1 | J26: =H26*I26 -> 690.8 | K26: =J26 -> 690.8 | L26: 193 | M26: 193 | N26: =M26-L26 -> 0 | O26: 4.4 | P26: =O26*N26 -> 0 | Q26: 690
A27: 16 | B27: 代家静 | C27: 车间 | D27: 135380 | E27: 458.7 | F27: 436.9 | G27: 40 | H27: =(E27-F27)*G27 -> 872 | I27: 1.1 | J27: =H27*I27 -> 959.2 | K27: =J27 -> 959.2 | L27: 207 | M27: 207 | N27: =M27-L27 -> 0 | O27: 4.4 | P27: =O27*N27 -> 0 | Q27: 959
A28: 17 | B28: 崔汝波 | C28: 车间 | D28: 135376 | E28: 50.6 | F28: 47.5 | G28: 40 | H28: =(E28-F28)*G28 -> 124 | I28: 1.1 | J28: =H28*I28 -> 136.4 | K28: =J28 -> 136.4 | L28: 80 | M28: 80 | N28: =M28-L28 -> 0 | O28: 4.4 | P28: =O28*N28 -> 0 | Q28: 136
A29: 18 | B29: 崔大洪 | C29: 车间 | D29: 无 | E29: 868 | F29: 820 | G29: 1 | H29: =(E29-F29)*G29 -> 48 | I29: 1.1 | J29: =H29*I29 -> 52.8 | K29: =J29 -> 52.8 | L29: 17 | M29: 17 | N29: =M29-L29 -> 0 | O29: 4.4 | P29: =O29*N29 -> 0 | Q29: 53
A30: 19 | B30: 崔大云 | C30: 车间 | D30: 无 | E30: 4043 | F30: 3848 | G30: 1 | H30: =(E30-F30)*G30 -> 195 | I30: 1.1 | J30: =H30*I30 -> 214.5 | K30: =J30 -> 214.5 | L30: 83 | M30: 83 | N30: =M30-L30 -> 0 | O30: 4.4 | P30: =O30*N30 -> 0 | Q30: 214.5
A31: 20 | B31: 冯成 | C31: 车间 | D31: 281917 | E31: 148.6 | F31: 134.9 | G31: 100 | H31: =(E31-F31)*G31 -> 1370 | I31: 1.1 | J31: =H31*I31 -> 1507 | K31: =J31 -> 1507 | L31: 14 | M31: 14 | N31: =M31-L31 -> 0 | O31: 4.4 | P31: =O31*N31 -> 0 | Q31: 1507
A32: 21 | B32: 崔汝义 | C32: 车间 | D32: 136865 | E32: 436.5 | F32: 405.5 | G32: 20 | H32: =(E32-F32)*G32 -> 620 | I32: 1.1 | J32: =H32*I32 -> 682 | K32: =J32 -> 682 | L32: 7 | M32: 7 | N32: =M32-L32 -> 0 | O32: 4.4 | P32: =O32*N32 -> 0 | Q32: 682
A33: 22 | B33: 崔文交 | C33: 车间 | D33: 121780 | E33: 114.1 | F33: 103.9 | G33: 20 | H33: =(E33-F33)*G33 -> 204 | I33: 1.1 | J33: =H33*I33 -> 224.4 | K33: =J33 -> 224.4 | L33: 89 | M33: 89 | N33: =M33-L33 -> 0 | O33: 4.4 | P33: =O33*N33 -> 0 | Q33: 225
A34: 23 | B34: 马世平 | C34: 车间 | D34: 135940 | E34: 73 | F34: 70.4 | G34: 30 | H34: =(E34-F34)*G34 -> 78 | I34: 1.1 | J34: =H34*I34 -> 85.8 | K34: =J34 -> 85.8 | L34: 7 | M34: 7 | N34: =M34-L34 -> 0 | O34: 4.4 | P34: =O34*N34 -> 0 | Q34: 86
A35: 24 | B35: 崔文洪 | C35: 车间 | D35: 121780 | E35: 4581.2 | F35: 4415.1 | G35: 30 | H35: =(E35-F35)*G35 -> 4983 | I35: 1.1 | J35: =H35*I35 -> 5481.3 | K35: 0 | L35: 127 | M35: 127 | N35: =M35-L35 -> 0 | O35: 4.4 | P35: =O35*N35 -> 0
A36: 25 | B36: 昭通煜成再生资源有限公司 | C36: 宿舍 | D36: 无 | E36: 229 | F36: 204 | G36: 1 | H36: =(E36-F36)*G36 -> 25 | I36: 1.1 | J36: =H36*I36 -> 27.5 | K36: =J36+J37 -> 3274.7 | L36: 73 | M36: 73 | N36: =M36-L36 -> 0 | O36: 4.4 | P36: =O36*N36 -> 0 | Q36: 3274.7
C37: 车间 | D37: 134768 | E37: 1152.1 | F37: 1115.2 | G37: 80 | H37: =(E37-F37)*G37 -> 2952 | I37: 1.1 | J37: =H37*I37 -> 3247.2 | N37: =M37-L37 -> 0 | O37: 4.4 | P37: =O37*N37 -> 0
A38: 26 | B38: 杨文仁 | C38: 车间 | D38: 135939 | E38: 340.8 | F38: 271.4 | G38: 80 | H38: =(E38-F38)*G38 -> 5552 | I38: 1.1 | J38: =H38*I38 -> 6107.2 | K38: =J38+J39 -> 19879.2 | L38: 2 | M38: 2 | N38: =M38-L38 -> 0 | O38: 4.4 | P38: =O38*N38 -> 0 | Q38: 10000 | R38: =K38-Q38 -> 9879.2
C39: 车间 | D39: 121779 | E39: 261.6 | F39: 136.4 | G39: 100 | H39: =(E39-F39)*G39 -> 12520 | I39: 1.1 | J39: =H39*I39 -> 13772
A40: 27 | B40: 创峰建材 | C40: 车间 | D40: 134773 | E40: 177.7 | F40: 152.2 | G40: 80 | H40: =(E40-F40)*G40 -> 2040 | I40: 1.1 | J40: =H40*I40 -> 2244 | K40: =J40 -> 2244 | L40: 8 | M40: 8 | N40: =M40-L40 -> 0 | O40: 4.4 | P40: =O40*N40 -> 0 | Q40: 2244
H41: =SUM(H4:H40) -> 51208 | J41: =SUM(J4:J40) -> 56328.8 | K41: =SUM(K4:K40) -> 50847.5 | N41: =SUM(N4:N40) -> 0 | Q41: =SUM(Q4:Q40) -> 40963.4
A42: 餐费： | C42: 1355餐费+80饭盒 | Q42: 2390
A43: 报销： | C43: 草酸 50斤*3桶 | Q43: 219
C44: TraeAPI | Q44: 52
C45: 正泰NS2-80B AU11 25-40A 40-63A 深井泵用断路器 | Q45: 247
C46: 小蒋申购T型刀片BS310019*5盒 | Q46: 25
C47: 小蒋申购波斯钢丝钳7寸 | Q47: 44.8
C48: 三月份扫地杂工：2月15号：3个工、3月8号：3个工、3月15号：3个工、3月22号：3个工、3月29号：3个工、总9个工：180×15=2700 | Q48: 2700
C49: 二月电费 | Q49: =25484.26*1.001 -> 25509.744
C50: 上月电费结转 | Q50: =-'2026年2月水电费'!S57 -> 43.71188
C51: 赔偿崔宇文过磅差额 | Q51: 900
C52: 赵庆昌 191.7
C53: 余波：21桶水21*7=147 20把竹扫把20*7=140元 | Q53: 287
C54: 火山引擎Coding plan | Q54: 50
C56: 蒋安坤购买水泵空开 | Q56: 235
A57: 小计： | Q57: =SUM(Q42:Q56) -> 32703.256
A58: 余额： | Q58: =Q41-Q57 -> 8260.1439
